Workbook

Sheet Resumen
A1: RESUMEN · 136 facturas 2.0TD · abril 2026 · Transactiva 2000 S.L.
A2: APROBAR ≥30% · REVISAR 20–30% · RECHAZAR <20% · objetivo editable en Detalle!G1. PC provisional (ámbar) → sustituir por real. Excedentes = kWh reales.
A4: Factura | B4: Cliente | C4: Nombre | D4: Prov. | E4: Margen abril | F4: Veredicto | G4: Margen hist. | H4: Cobrado hist. | I4: Qué revisar
A5: 8550 | B5: C02150 | C5: FUNDACIÓN FSU PROGRAMAS INTERNACIO | D5: Naturgy | E5: =Detalle!B15 -> 0.32906535 | F5: =Detalle!D15 -> APROBAR | G5: 0.2802 | H5: 2435.51 | I5: =IF(Detalle!B15="","Falta PC real",IF(Detalle!B15>=Detalle!$G$1,"OK · registrar",IF(Detalle!B15>=0.2,"Revisar margen","Revisar PC/PV"))) -> OK · registrar
A6: 8551 | B6: C02140 | C6: FUNDACIÓN FSU PROGRAMAS INTERNACIO | D6: Naturgy | E6: =Detalle!B29 -> 0.32791454 | F6: =Detalle!D29 -> APROBAR | G6: 0.2374 | H6: 2120.45 | I6: =IF(Detalle!B29="","Falta PC real",IF(Detalle!B29>=Detalle!$G$1,"OK · registrar",IF(Detalle!B29>=0.2,"Revisar margen","Revisar PC/PV"))) -> OK · registrar
A7: 8552 | B7: C02130 | C7: FUNDACIÓN FSU PROGRAMAS INTERNACIO | D7: Naturgy | E7: =Detalle!B43 -> 0.33776615 | F7: =Detalle!D43 -> APROBAR | G7: 0.3004 | H7: 3194.42 | I7: =IF(Detalle!B43="","Falta PC real",IF(Detalle!B43>=Detalle!$G$1,"OK · registrar",IF(Detalle!B43>=0.2,"Revisar margen","Revisar PC/PV"))) -> OK · registrar
A8: 8553 | B8: C02120 | C8: FUNDACIÓN FSU PROGRAMAS INTERNACIO | D8: Naturgy | E8: =Detalle!B57 -> 0.18652025 | F8: =Detalle!D57 -> RECHAZAR | G8: 0.2933 | H8: 2606.28 | I8: =IF(Detalle!B57="","Falta PC real",IF(Detalle!B57>=Detalle!$G$1,"OK · registrar",IF(Detalle!B57>=0.2,"Revisar margen","Revisar PC/PV"))) -> Revisar PC/PV
A9: 8554 | B9: C02110 | C9: FUNDACIÓN FSU PROGRAMAS INTERNACIO | D9: Naturgy | E9: =Detalle!B71 -> 0.33884194 | F9: =Detalle!D71 -> APROBAR | G9: 0.3099 | H9: 5248.88 | I9: =IF(Detalle!B71="","Falta PC real",IF(Detalle!B71>=Detalle!$G$1,"OK · registrar",IF(Detalle!B71>=0.2,"Revisar margen","Revisar PC/PV"))) -> OK · registrar
A10: 8555 | B10: C02100 | C10: FUNDACIÓN FSU PROGRAMAS INTERNACIO | D10: Naturgy | E10: =Detalle!B85 -> 0.33604893 | F10: =Detalle!D85 -> APROBAR | G10: 0.3022 | H10: 1841.6 | I10: =IF(Detalle!B85="","Falta PC real",IF(Detalle!B85>=Detalle!$G$1,"OK · registrar",IF(Detalle!B85>=0.2,"Revisar margen","Revisar PC/PV"))) -> OK · registrar
A11: 8556 | B11: C02090 | C11: FUNDACIÓN FSU PROGRAMAS INTERNACIO | D11: Naturgy | E11: =Detalle!B99 -> 0.33892336 | F11: =Detalle!D99 -> APROBAR | G11: 0.2895 | H11: 2954.17 | I11: =IF(Detalle!B99="","Falta PC real",IF(Detalle!B99>=Detalle!$G$1,"OK · registrar",IF(Detalle!B99>=0.2,"Revisar margen","Revisar PC/PV"))) -> OK · registrar
A12: 8557 | B12: C02080 | C12: FUNDACIÓN FSU PROGRAMAS INTERNACIO | D12: Naturgy | E12: =Detalle!B113 -> 0.33246101 | F12: =Detalle!D113 -> APROBAR | I12: =IF(Detalle!B113="","Falta PC real",IF(Detalle!B113>=Detalle!$G$1,"OK · registrar",IF(Detalle!B113>=0.2,"Revisar margen","Revisar PC/PV"))) -> OK · registrar
A13: 8558 | B13: C02060 | C13: FUNDACIÓN FSU PROGRAMAS INTERNACIO | D13: Naturgy | E13: =Detalle!B127 -> 0.3356097 | F13: =Detalle!D127 -> APROBAR | G13: 0.293 | H13: 3233.11 | I13: =IF(Detalle!B127="","Falta PC real",IF(Detalle!B127>=Detalle!$G$1,"OK · registrar",IF(Detalle!B127>=0.2,"Revisar margen","Revisar PC/PV"))) -> OK · registrar
A14: 8559 | B14: C02040 | C14: FUNDACIÓN FSU PROGRAMAS INTERNACIO | D14: Naturgy | E14: =Detalle!B141 -> 0.32177702 | F14: =Detalle!D141 -> APROBAR | G14: 0.3314 | H14: 989.5 | I14: =IF(Detalle!B141="","Falta PC real",IF(Detalle!B141>=Detalle!$G$1,"OK · registrar",IF(Detalle!B141>=0.2,"Revisar margen","Revisar PC/PV"))) -> OK · registrar
A15: 8560 | B15: C02030 | C15: FUNDACIÓN FSU PROGRAMAS INTERNACIO | D15: Naturgy | E15: =Detalle!B155 -> 0.32654455 | F15: =Detalle!D155 -> APROBAR | G15: 0.2482 | H15: 837.32 | I15: =IF(Detalle!B155="","Falta PC real",IF(Detalle!B155>=Detalle!$G$1,"OK · registrar",IF(Detalle!B155>=0.2,"Revisar margen","Revisar PC/PV"))) -> OK · registrar
A16: 8561 | B16: C02020 | C16: FUNDACIÓN FSU PROGRAMAS INTERNACIO | D16: Naturgy | E16: =Detalle!B169 -> 0.33709853 | F16: =Detalle!D169 -> APROBAR | G16: 0.2981 | H16: 3102.69 | I16: =IF(Detalle!B169="","Falta PC real",IF(Detalle!B169>=Detalle!$G$1,"OK · registrar",IF(Detalle!B169>=0.2,"Revisar margen","Revisar PC/PV"))) -> OK · registrar
A17: 8562 | B17: C01970 | C17: FUNDACIÓN FSU PROGRAMAS INTERNACIO | D17: Naturgy | E17: =Detalle!B183 -> 0.3310343 | F17: =Detalle!D183 -> APROBAR | G17: 0.295 | H17: 2842.61 | I17: =IF(Detalle!B183="","Falta PC real",IF(Detalle!B183>=Detalle!$G$1,"OK · registrar",IF(Detalle!B183>=0.2,"Revisar margen","Revisar PC/PV"))) -> OK · registrar
A18: 8563 | B18: C01960 | C18: FUNDACIÓN FSU PROGRAMAS INTERNACIO | D18: Naturgy | E18: =Detalle!B197 -> 0.33306586 | F18: =Detalle!D197 -> APROBAR | G18: 0.3206 | H18: 3731.12 | I18: =IF(Detalle!B197="","Falta PC real",IF(Detalle!B197>=Detalle!$G$1,"OK · registrar",IF(Detalle!B197>=0.2,"Revisar margen","Revisar PC/PV"))) -> OK · registrar
A19: 8568 | B19: C01400 | C19: CHRISTOPH BLUME | D19: Naturgy | E19: =Detalle!B211 -> 0.24260659 | F19: =Detalle!D211 -> REVISAR | G19: 0.3031 | H19: 2280.53 | I19: =IF(Detalle!B211="","Falta PC real",IF(Detalle!B211>=Detalle!$G$1,"OK · registrar",IF(Detalle!B211>=0.2,"Revisar margen","Revisar PC/PV"))) -> Revisar margen
A20: 8569 | B20: C02560 | C20: PEDRO IVARS TRO 2018, S.L. | D20: Naturgy | E20: =Detalle!B230 -> 0.13627977 | F20: =Detalle!D230 -> RECHAZAR | G20: 0.354 | H20: 452.94 | I20: =IF(Detalle!B230="","Falta PC real",IF(Detalle!B230>=Detalle!$G$1,"OK · registrar",IF(Detalle!B230>=0.2,"Revisar margen","Revisar PC/PV"))) -> Revisar PC/PV
A21: 8570 | B21: C02680 | C21: ALVARO DAVID OCHOA BIOSCA | D21: Naturgy | E21: =Detalle!B244 -> 0.15852433 | F21: =Detalle!D244 -> RECHAZAR | G21: 1 | H21: 2.65 | I21: =IF(Detalle!B244="","Falta PC real",IF(Detalle!B244>=Detalle!$G$1,"OK · registrar",IF(Detalle!B244>=0.2,"Revisar margen","Revisar PC/PV"))) -> Revisar PC/PV
A22: 8571 | B22: C00700 | C22: ELEEN VELTHOVEN | D22: Naturgy | E22: =Detalle!B258 -> 0.22717695 | F22: =Detalle!D258 -> REVISAR | G22: 0.1991 | H22: 1674.46 | I22: =IF(Detalle!B258="","Falta PC real",IF(Detalle!B258>=Detalle!$G$1,"OK · registrar",IF(Detalle!B258>=0.2,"Revisar margen","Revisar PC/PV"))) -> Revisar margen
A23: 8572 | B23: C01280 | C23: Mª ISABEL HEVIA TENA | D23: Naturgy | E23: =Detalle!B277 -> 0.2171288 | F23: =Detalle!D277 -> REVISAR | G23: 0.3077 | H23: 2373.43 | I23: =IF(Detalle!B277="","Falta PC real",IF(Detalle!B277>=Detalle!$G$1,"OK · registrar",IF(Detalle!B277>=0.2,"Revisar margen","Revisar PC/PV"))) -> Revisar margen
A24: 8573 | B24: C01990 | C24: GERRIT JONGEJAN | D24: Naturgy | E24: =Detalle!B296 -> 0.26733195 | F24: =Detalle!D296 -> REVISAR | G24: 0.0538 | H24: 609.46 | I24: =IF(Detalle!B296="","Falta PC real",IF(Detalle!B296>=Detalle!$G$1,"OK · registrar",IF(Detalle!B296>=0.2,"Revisar margen","Revisar PC/PV"))) -> Revisar margen
A25: 8574 | B25: C03260 | C25: MICHAL CUKAN | D25: Naturgy | E25: =Detalle!B315 -> 0.098462768 | F25: =Detalle!D315 -> RECHAZAR | G25: 1 | H25: 0.86 | I25: =IF(Detalle!B315="","Falta PC real",IF(Detalle!B315>=Detalle!$G$1,"OK · registrar",IF(Detalle!B315>=0.2,"Revisar margen","Revisar PC/PV"))) -> Revisar PC/PV
A26: 8575 | B26: C01140 | C26: DESIRÉ ANNA GUSTAAF SCHUTTER | D26: Naturgy | E26: =Detalle!B329 -> 0.14690105 | F26: =Detalle!D329 -> RECHAZAR | G26: 0.2556 | H26: 1316.57 | I26: =IF(Detalle!B329="","Falta PC real",IF(Detalle!B329>=Detalle!$G$1,"OK · registrar",IF(Detalle!B329>=0.2,"Revisar margen","Revisar PC/PV"))) -> Revisar PC/PV
A27: 8579 | B27: C01350 | C27: CORDULA PETERS | D27: Naturgy | E27: =Detalle!B348 -> 0.13397764 | F27: =Detalle!D348 -> RECHAZAR | G27: 0.0004 | H27: 638.64 | I27: =IF(Detalle!B348="","Falta PC real",IF(Detalle!B348>=Detalle!$G$1,"OK · registrar",IF(Detalle!B348>=0.2,"Revisar margen","Revisar PC/PV"))) -> Revisar PC/PV
A28: 8580 | B28: C00060 | C28: HV LUXO SA | D28: Naturgy | E28: =Detalle!B367 -> 0.22771278 | F28: =Detalle!D367 -> REVISAR | G28: 0.4727 | H28: 1556.34 | I28: =IF(Detalle!B367="","Falta PC real",IF(Detalle!B367>=Detalle!$G$1,"OK · registrar",IF(Detalle!B367>=0.2,"Revisar margen","Revisar PC/PV"))) -> Revisar margen
A29: 8581 | C29: MANUEL GARCÍA DEL VALLE CARLOS-ROC | D29: Naturgy | E29: =Detalle!B386 -> 0.090771272 | F29: =Detalle!D386 -> RECHAZAR | G29: 0.178 | H29: 3463.21 | I29: =IF(Detalle!B386="","Falta PC real",IF(Detalle!B386>=Detalle!$G$1,"OK · registrar",IF(Detalle!B386>=0.2,"Revisar margen","Revisar PC/PV"))) -> Revisar PC/PV
A30: 8584 | B30: C00040 | C30: Mª ROSARIO ORTOLÁ FERRER | D30: Naturgy | E30: =Detalle!B400 -> 0.21379897 | F30: =Detalle!D400 -> REVISAR | G30: 0.3577 | H30: 10840.8 | I30: =IF(Detalle!B400="","Falta PC real",IF(Detalle!B400>=Detalle!$G$1,"OK · registrar",IF(Detalle!B400>=0.2,"Revisar margen","Revisar PC/PV"))) -> Revisar margen
A31: 8585 | B31: C00050 | C31: HELADOS ESPI | D31: Naturgy | E31: =Detalle!B419 -> 0.18511231 | F31: =Detalle!D419 -> RECHAZAR | G31: 0.301 | H31: 5330.72 | I31: =IF(Detalle!B419="","Falta PC real",IF(Detalle!B419>=Detalle!$G$1,"OK · registrar",IF(Detalle!B419>=0.2,"Revisar margen","Revisar PC/PV"))) -> Revisar PC/PV
A32: 8586 | B32: C00060 | C32: HV LUXO SA | D32: Naturgy | E32: =Detalle!B438 -> 0.22771278 | F32: =Detalle!D438 -> REVISAR | G32: 0.4727 | H32: 1556.34 | I32: =IF(Detalle!B438="","Falta PC real",IF(Detalle!B438>=Detalle!$G$1,"OK · registrar",IF(Detalle!B438>=0.2,"Revisar margen","Revisar PC/PV"))) -> Revisar margen
A33: 8588 | B33: C00100 | C33: CRISTINA MARÍA FALCÓN ESCALONA | D33: Naturgy | E33: =Detalle!B457 -> 0.37156635 | F33: =Detalle!D457 -> APROBAR | G33: 0.4676 | H33: 1874.26 | I33: =IF(Detalle!B457="","Falta PC real",IF(Detalle!B457>=Detalle!$G$1,"OK · registrar",IF(Detalle!B457>=0.2,"Revisar margen","Revisar PC/PV"))) -> OK · registrar
A34: 8589 | B34: C00120 | C34: STEPHEN RICHARD ROBINSON | D34: Naturgy | E34: =Detalle!B476 -> 0.32105091 | F34: =Detalle!D476 -> APROBAR | G34: 0.3197 | H34: 3583.48 | I34: =IF(Detalle!B476="","Falta PC real",IF(Detalle!B476>=Detalle!$G$1,"OK · registrar",IF(Detalle!B476>=0.2,"Revisar margen","Revisar PC/PV"))) -> OK · registrar
A35: 8590 | B35: C00130 | C35: BIO JARDINSOSTENIBLE, S.L.U. | D35: Naturgy | E35: =Detalle!B495 -> 0.23206358 | F35: =Detalle!D495 -> REVISAR | G35: 0.4296 | H35: 3448.6 | I35: =IF(Detalle!B495="","Falta PC real",IF(Detalle!B495>=Detalle!$G$1,"OK · registrar",IF(Detalle!B495>=0.2,"Revisar margen","Revisar PC/PV"))) -> Revisar margen
A36: 8593 | B36: C00270 | C36: CLAUDE JOSÉ GOFFINET | D36: Naturgy | E36: =Detalle!B514 -> 0.16757774 | F36: =Detalle!D514 -> RECHAZAR | G36: 0.46 | H36: 4468.12 | I36: =IF(Detalle!B514="","Falta PC real",IF(Detalle!B514>=Detalle!$G$1,"OK · registrar",IF(Detalle!B514>=0.2,"Revisar margen","Revisar PC/PV"))) -> Revisar PC/PV
A37: 8594 | B37: C00310 | C37: MICHAEL BALMER | D37: Naturgy | E37: =Detalle!B533 -> 0.1226697 | F37: =Detalle!D533 -> RECHAZAR | G37: 0.5097 | H37: 1087.08 | I37: =IF(Detalle!B533="","Falta PC real",IF(Detalle!B533>=Detalle!$G$1,"OK · registrar",IF(Detalle!B533>=0.2,"Revisar margen","Revisar PC/PV"))) -> Revisar PC/PV
A38: 8597 | B38: C00410 | C38: VALENTINA BARCA | D38: Naturgy | E38: =Detalle!B552 -> 0.17187272 | F38: =Detalle!D552 -> RECHAZAR | G38: 0.3904 | H38: 3173.99 | I38: =IF(Detalle!B552="","Falta PC real",IF(Detalle!B552>=Detalle!$G$1,"OK · registrar",IF(Detalle!B552>=0.2,"Revisar margen","Revisar PC/PV"))) -> Revisar PC/PV
A39: 8599 | B39: C00540 | C39: PEDRO CAÑADAS FERNANDEZ | D39: Naturgy | E39: =Detalle!B571 -> 0.15909925 | F39: =Detalle!D571 -> RECHAZAR | G39: 0.2884 | H39: 910.46 | I39: =IF(Detalle!B571="","Falta PC real",IF(Detalle!B571>=Detalle!$G$1,"OK · registrar",IF(Detalle!B571>=0.2,"Revisar margen","Revisar PC/PV"))) -> Revisar PC/PV
A40: 8600 | B40: C00670 | C40: CARLOS A. GAVILANES PAUCAR | D40: Naturgy | E40: =Detalle!B590 -> 0.18955947 | F40: =Detalle!D590 -> RECHAZAR | G40: 0.4352 | H40: 5027.47 | I40: =IF(Detalle!B590="","Falta PC real",IF(Detalle!B590>=Detalle!$G$1,"OK · registrar",IF(Detalle!B590>=0.2,"Revisar margen","Revisar PC/PV"))) -> Revisar PC/PV
A41: 8601 | B41: C00700 | C41: ELEEN VELTHOVEN | D41: Naturgy | E41: =Detalle!B604 -> 0.22717695 | F41: =Detalle!D604 -> REVISAR | G41: 0.1991 | H41: 1674.46 | I41: =IF(Detalle!B604="","Falta PC real",IF(Detalle!B604>=Detalle!$G$1,"OK · registrar",IF(Detalle!B604>=0.2,"Revisar margen","Revisar PC/PV"))) -> Revisar margen
A42: 8604 | B42: C00780 | C42: MONTGO SEGURIDAD, S.L. | D42: Naturgy | E42: =Detalle!B623 -> 0.18578471 | F42: =Detalle!D623 -> RECHAZAR | G42: 0.0918 | H42: 1103.81 | I42: =IF(Detalle!B623="","Falta PC real",IF(Detalle!B623>=Detalle!$G$1,"OK · registrar",IF(Detalle!B623>=0.2,"Revisar margen","Revisar PC/PV"))) -> Revisar PC/PV
A43: 8605 | B43: C00820 | C43: JAIME VIVES LADRÓN DE GUEVARA | D43: Naturgy | E43: =Detalle!B642 -> 0.15890509 | F43: =Detalle!D642 -> RECHAZAR | G43: 0.3695 | H43: 1904.3 | I43: =IF(Detalle!B642="","Falta PC real",IF(Detalle!B642>=Detalle!$G$1,"OK · registrar",IF(Detalle!B642>=0.2,"Revisar margen","Revisar PC/PV"))) -> Revisar PC/PV
A44: 8606 | B44: C00910 | C44: PATRICE HERNEST HECQ | D44: Naturgy | E44: =Detalle!B661 -> 0.31391134 | F44: =Detalle!D661 -> APROBAR | G44: 0.4652 | H44: 1466.53 | I44: =IF(Detalle!B661="","Falta PC real",IF(Detalle!B661>=Detalle!$G$1,"OK · registrar",IF(Detalle!B661>=0.2,"Revisar margen","Revisar PC/PV"))) -> OK · registrar
A45: 8607 | B45: C00940 | C45: ANDRE DOUTREVAL | D45: Naturgy | E45: =Detalle!B680 -> 0.2302119 | F45: =Detalle!D680 -> REVISAR | G45: 0.4936 | H45: 2318.26 | I45: =IF(Detalle!B680="","Falta PC real",IF(Detalle!B680>=Detalle!$G$1,"OK · registrar",IF(Detalle!B680>=0.2,"Revisar margen","Revisar PC/PV"))) -> Revisar margen
A46: 8611 | B46: C01140 | C46: DESIRÉ ANNA GUSTAAF SCHUTTER | D46: Naturgy | E46: =Detalle!B699 -> 0.14690105 | F46: =Detalle!D699 -> RECHAZAR | G46: 0.2556 | H46: 1316.57 | I46: =IF(Detalle!B699="","Falta PC real",IF(Detalle!B699>=Detalle!$G$1,"OK · registrar",IF(Detalle!B699>=0.2,"Revisar margen","Revisar PC/PV"))) -> Revisar PC/PV
A47: 8612 | B47: C01150 | C47: ARIE PETER PETRI | D47: Naturgy | E47: =Detalle!B718 -> 0.17700951 | F47: =Detalle!D718 -> RECHAZAR | G47: 0.3724 | H47: 2947.02 | I47: =IF(Detalle!B718="","Falta PC real",IF(Detalle!B718>=Detalle!$G$1,"OK · registrar",IF(Detalle!B718>=0.2,"Revisar margen","Revisar PC/PV"))) -> Revisar PC/PV
A48: 8613 | B48: C01160 | C48: DEBORAH LEFFELAAR | D48: Naturgy | E48: =Detalle!B737 -> 0.14359752 | F48: =Detalle!D737 -> RECHAZAR | G48: 0.4239 | H48: 3342.92 | I48: =IF(Detalle!B737="","Falta PC real",IF(Detalle!B737>=Detalle!$G$1,"OK · registrar",IF(Detalle!B737>=0.2,"Revisar margen","Revisar PC/PV"))) -> Revisar PC/PV
A49: 8614 | B49: C01190 | C49: BART VAN OERLE JOZEF J. | D49: Naturgy | E49: =Detalle!B756 -> 0.20168061 | F49: =Detalle!D756 -> REVISAR | G49: 0.323 | H49: 755.04 | I49: =IF(Detalle!B756="","Falta PC real",IF(Detalle!B756>=Detalle!$G$1,"OK · registrar",IF(Detalle!B756>=0.2,"Revisar margen","Revisar PC/PV"))) -> Revisar margen
A50: 8617 | B50: C01250 | C50: DANIELLE B. PAULI | D50: Naturgy | E50: =Detalle!B775 -> 0.14238296 | F50: =Detalle!D775 -> RECHAZAR | G50: 0.3445 | H50: 840.98 | I50: =IF(Detalle!B775="","Falta PC real",IF(Detalle!B775>=Detalle!$G$1,"OK · registrar",IF(Detalle!B775>=0.2,"Revisar margen","Revisar PC/PV"))) -> Revisar PC/PV
A51: 8618 | B51: C01280 | C51: Mª ISABEL HEVIA TENA | D51: Naturgy | E51: =Detalle!B794 -> 0.2171288 | F51: =Detalle!D794 -> REVISAR | G51: 0.3077 | H51: 2373.43 | I51: =IF(Detalle!B794="","Falta PC real",IF(Detalle!B794>=Detalle!$G$1,"OK · registrar",IF(Detalle!B794>=0.2,"Revisar margen","Revisar PC/PV"))) -> Revisar margen
A52: 8620 | B52: C01330 | C52: ULF BALZER | D52: Naturgy | E52: =Detalle!B813 -> 0.21233962 | F52: =Detalle!D813 -> REVISAR | G52: 0.3424 | H52: 1175.92 | I52: =IF(Detalle!B813="","Falta PC real",IF(Detalle!B813>=Detalle!$G$1,"OK · registrar",IF(Detalle!B813>=0.2,"Revisar margen","Revisar PC/PV"))) -> Revisar margen
A53: 8621 | B53: C01350 | C53: CORDULA PETERS | D53: Naturgy | E53: =Detalle!B832 -> 0.13397764 | F53: =Detalle!D832 -> RECHAZAR | G53: 0.0004 | H53: 638.64 | I53: =IF(Detalle!B832="","Falta PC real",IF(Detalle!B832>=Detalle!$G$1,"OK · registrar",IF(Detalle!B832>=0.2,"Revisar margen","Revisar PC/PV"))) -> Revisar PC/PV
A54: 8622 | B54: C01390 | C54: DANIEL DE WIT | D54: Naturgy | E54: =Detalle!B851 -> 0.36428091 | F54: =Detalle!D851 -> APROBAR | G54: 0.3128 | H54: 4238.97 | I54: =IF(Detalle!B851="","Falta PC real",IF(Detalle!B851>=Detalle!$G$1,"OK · registrar",IF(Detalle!B851>=0.2,"Revisar margen","Revisar PC/PV"))) -> OK · registrar
A55: 8623 | B55: C01400 | C55: CHRISTOPH BLUME | D55: Naturgy | E55: =Detalle!B870 -> 0.24260659 | F55: =Detalle!D870 -> REVISAR | G55: 0.3031 | H55: 2280.53 | I55: =IF(Detalle!B870="","Falta PC real",IF(Detalle!B870>=Detalle!$G$1,"OK · registrar",IF(Detalle!B870>=0.2,"Revisar margen","Revisar PC/PV"))) -> Revisar margen
A56: 8624 | B56: C01420 | C56: JAIME VIVES | D56: Naturgy | E56: =Detalle!B889 -> 0.10957942 | F56: =Detalle!D889 -> RECHAZAR | G56: 0.271 | H56: 3219.58 | I56: =IF(Detalle!B889="","Falta PC real",IF(Detalle!B889>=Detalle!$G$1,"OK · registrar",IF(Detalle!B889>=0.2,"Revisar margen","Revisar PC/PV"))) -> Revisar PC/PV
A57: 8625 | B57: C01440 | C57: VICENTE BAS ALENTADO | D57: Naturgy | E57: =Detalle!B903 -> 0.11508415 | F57: =Detalle!D903 -> RECHAZAR | G57: 0.2944 | H57: 1840.65 | I57: =IF(Detalle!B903="","Falta PC real",IF(Detalle!B903>=Detalle!$G$1,"OK · registrar",IF(Detalle!B903>=0.2,"Revisar margen","Revisar PC/PV"))) -> Revisar PC/PV
A58: 8626 | B58: C01460 | C58: MARCUS JOHANNES MULLER | D58: Naturgy | E58: =Detalle!B917 -> 0.12597943 | F58: =Detalle!D917 -> RECHAZAR | G58: 0.0856 | H58: 936.83 | I58: =IF(Detalle!B917="","Falta PC real",IF(Detalle!B917>=Detalle!$G$1,"OK · registrar",IF(Detalle!B917>=0.2,"Revisar margen","Revisar PC/PV"))) -> Revisar PC/PV
A59: 8627 | B59: C01470 | C59: LIEUWE KOOPMANS | D59: Naturgy | E59: =Detalle!B936 -> 0.16025977 | F59: =Detalle!D936 -> RECHAZAR | G59: 0.3038 | H59: 1173.88 | I59: =IF(Detalle!B936="","Falta PC real",IF(Detalle!B936>=Detalle!$G$1,"OK · registrar",IF(Detalle!B936>=0.2,"Revisar margen","Revisar PC/PV"))) -> Revisar PC/PV
A60: 8628 | B60: C01490 | C60: JOSE EDUARDO BAYONA SOTOS | D60: Naturgy | E60: =Detalle!B955 -> 0.14261813 | F60: =Detalle!D955 -> RECHAZAR | G60: 0.2292 | H60: 3231.67 | I60: =IF(Detalle!B955="","Falta PC real",IF(Detalle!B955>=Detalle!$G$1,"OK · registrar",IF(Detalle!B955>=0.2,"Revisar margen","Revisar PC/PV"))) -> Revisar PC/PV
A61: 8630 | B61: C01530 | C61: JUAN POCH FERNANDEZ | D61: Naturgy | E61: =Detalle!B969 -> 0.23249933 | F61: =Detalle!D969 -> REVISAR | G61: 0.378 | H61: 2148.32 | I61: =IF(Detalle!B969="","Falta PC real",IF(Detalle!B969>=Detalle!$G$1,"OK · registrar",IF(Detalle!B969>=0.2,"Revisar margen","Revisar PC/PV"))) -> Revisar margen
A62: 8631 | B62: C01540 | C62: FORN MONICA S L | D62: Naturgy | E62: =Detalle!B988 -> 0.0022438085 | F62: =Detalle!D988 -> RECHAZAR | G62: 0.3244 | H62: 13789.11 | I62: =IF(Detalle!B988="","Falta PC real",IF(Detalle!B988>=Detalle!$G$1,"OK · registrar",IF(Detalle!B988>=0.2,"Revisar margen","Revisar PC/PV"))) -> Revisar PC/PV
A63: 8632 | B63: C01570 | C63: FRANCISCO MULA ROBERTO | D63: Naturgy | E63: =Detalle!B1002 -> 0.19380389 | F63: =Detalle!D1002 -> RECHAZAR | G63: 0.368 | H63: 1850.34 | I63: =IF(Detalle!B1002="","Falta PC real",IF(Detalle!B1002>=Detalle!$G$1,"OK · registrar",IF(Detalle!B1002>=0.2,"Revisar margen","Revisar PC/PV"))) -> Revisar PC/PV
A64: 8633 | B64: C01600 | C64: HAFELI BRIGITTE | D64: Naturgy | E64: =Detalle!B1016 -> 0.20474588 | F64: =Detalle!D1016 -> REVISAR | G64: 0.2792 | H64: 2070.05 | I64: =IF(Detalle!B1016="","Falta PC real",IF(Detalle!B1016>=Detalle!$G$1,"OK · registrar",IF(Detalle!B1016>=0.2,"Revisar margen","Revisar PC/PV"))) -> Revisar margen
A65: 8634 | B65: C01620 | C65: MIA EDELTRUDIS JOSEPHINA ZANTMAN | D65: Naturgy | E65: =Detalle!B1035 -> 0.2072125 | F65: =Detalle!D1035 -> REVISAR | G65: -0.824 | H65: 282.36 | I65: =IF(Detalle!B1035="","Falta PC real",IF(Detalle!B1035>=Detalle!$G$1,"OK · registrar",IF(Detalle!B1035>=0.2,"Revisar margen","Revisar PC/PV"))) -> Revisar margen
A66: 8636 | B66: C01660 | C66: LIEUWE KOOPMANS (2) | D66: Naturgy | E66: =Detalle!B1054 -> 0.16664573 | F66: =Detalle!D1054 -> RECHAZAR | G66: 0.2775 | H66: 2326.68 | I66: =IF(Detalle!B1054="","Falta PC real",IF(Detalle!B1054>=Detalle!$G$1,"OK · registrar",IF(Detalle!B1054>=0.2,"Revisar margen","Revisar PC/PV"))) -> Revisar PC/PV
A67: 8637 | B67: C01670 | C67: COCKTAIL BAR AYAHUMA | D67: Naturgy | E67: =Detalle!B1073 -> 0.23359395 | F67: =Detalle!D1073 -> REVISAR | G67: 0.3087 | H67: 5393.13 | I67: =IF(Detalle!B1073="","Falta PC real",IF(Detalle!B1073>=Detalle!$G$1,"OK · registrar",IF(Detalle!B1073>=0.2,"Revisar margen","Revisar PC/PV"))) -> Revisar margen
A68: 8639 | B68: C01720 | C68: AHMED DAHMAN | D68: Naturgy | E68: =Detalle!B1087 -> 0.14000007 | F68: =Detalle!D1087 -> RECHAZAR | G68: 0.336 | H68: 1989.67 | I68: =IF(Detalle!B1087="","Falta PC real",IF(Detalle!B1087>=Detalle!$G$1,"OK · registrar",IF(Detalle!B1087>=0.2,"Revisar margen","Revisar PC/PV"))) -> Revisar PC/PV
A69: 8640 | B69: C01730 | C69: LORENA ROCIO PAUCAR LÓPEZ | D69: Naturgy | E69: =Detalle!B1101 -> 0.17420079 | F69: =Detalle!D1101 -> RECHAZAR | G69: 0.3488 | H69: 7310.54 | I69: =IF(Detalle!B1101="","Falta PC real",IF(Detalle!B1101>=Detalle!$G$1,"OK · registrar",IF(Detalle!B1101>=0.2,"Revisar margen","Revisar PC/PV"))) -> Revisar PC/PV
A70: 8642 | B70: C01800 | C70: ROY SCHOLTEN | D70: Naturgy | E70: =Detalle!B1115 -> 0.20638693 | F70: =Detalle!D1115 -> REVISAR | G70: 0.2251 | H70: 1291.58 | I70: =IF(Detalle!B1115="","Falta PC real",IF(Detalle!B1115>=Detalle!$G$1,"OK · registrar",IF(Detalle!B1115>=0.2,"Revisar margen","Revisar PC/PV"))) -> Revisar margen
A71: 8645 | B71: C01850 | C71: GUILLERMO CHOLBI SART | D71: Naturgy | E71: =Detalle!B1134 -> 0.085012268 | F71: =Detalle!D1134 -> RECHAZAR | G71: 0.2601 | H71: 669.11 | I71: =IF(Detalle!B1134="","Falta PC real",IF(Detalle!B1134>=Detalle!$G$1,"OK · registrar",IF(Detalle!B1134>=0.2,"Revisar margen","Revisar PC/PV"))) -> Revisar PC/PV
A72: 8646 | B72: C01860 | C72: GUILLERMO CHOLBI SART | D72: Naturgy | E72: =Detalle!B1148 -> 0.1620213 | F72: =Detalle!D1148 -> RECHAZAR | G72: 0.1345 | H72: 3661.58 | I72: =IF(Detalle!B1148="","Falta PC real",IF(Detalle!B1148>=Detalle!$G$1,"OK · registrar",IF(Detalle!B1148>=0.2,"Revisar margen","Revisar PC/PV"))) -> Revisar PC/PV
A73: 8647 | B73: C01870 | C73: GUILLERMO CHOLBI SART | D73: Naturgy | E73: =Detalle!B1162 -> 0.12482477 | F73: =Detalle!D1162 -> RECHAZAR | G73: 0.1953 | H73: 1401.63 | I73: =IF(Detalle!B1162="","Falta PC real",IF(Detalle!B1162>=Detalle!$G$1,"OK · registrar",IF(Detalle!B1162>=0.2,"Revisar margen","Revisar PC/PV"))) -> Revisar PC/PV
A74: 8648 | B74: C01880 | C74: ALEJANDRO BOX CANDELA | D74: Naturgy | E74: =Detalle!B1176 -> 0.17853695 | F74: =Detalle!D1176 -> RECHAZAR | G74: 0.2432 | H74: 1364.97 | I74: =IF(Detalle!B1176="","Falta PC real",IF(Detalle!B1176>=Detalle!$G$1,"OK · registrar",IF(Detalle!B1176>=0.2,"Revisar margen","Revisar PC/PV"))) -> Revisar PC/PV
A75: 8650 | B75: C01990 | C75: GERRIT JONGEJAN | D75: Naturgy | E75: =Detalle!B1190 -> 0.26733195 | F75: =Detalle!D1190 -> REVISAR | G75: 0.0538 | H75: 609.46 | I75: =IF(Detalle!B1190="","Falta PC real",IF(Detalle!B1190>=Detalle!$G$1,"OK · registrar",IF(Detalle!B1190>=0.2,"Revisar margen","Revisar PC/PV"))) -> Revisar margen
A76: 8651 | B76: C02160 | C76: CASA LILI SL (V) | D76: Naturgy | E76: =Detalle!B1209 -> 0.15226639 | F76: =Detalle!D1209 -> RECHAZAR | G76: 0.3125 | H76: 2035.12 | I76: =IF(Detalle!B1209="","Falta PC real",IF(Detalle!B1209>=Detalle!$G$1,"OK · registrar",IF(Detalle!B1209>=0.2,"Revisar margen","Revisar PC/PV"))) -> Revisar PC/PV
A77: 8653 | B77: C02190 | C77: TAIRÉ VERA | D77: Naturgy | E77: =Detalle!B1223 -> 0.077195112 | F77: =Detalle!D1223 -> RECHAZAR | G77: 0.1189 | H77: 597.68 | I77: =IF(Detalle!B1223="","Falta PC real",IF(Detalle!B1223>=Detalle!$G$1,"OK · registrar",IF(Detalle!B1223>=0.2,"Revisar margen","Revisar PC/PV"))) -> Revisar PC/PV
A78: 8655 | B78: C02240 | C78: SANDRA GONZALEZ LECHUGA | D78: Naturgy | E78: =Detalle!B1237 -> 0.1593503 | F78: =Detalle!D1237 -> RECHAZAR | G78: -0.1267 | H78: 194.94 | I78: =IF(Detalle!B1237="","Falta PC real",IF(Detalle!B1237>=Detalle!$G$1,"OK · registrar",IF(Detalle!B1237>=0.2,"Revisar margen","Revisar PC/PV"))) -> Revisar PC/PV
A79: 8656 | B79: C02340 | C79: PRISCILA WELTER CARRASCO | D79: Naturgy | E79: =Detalle!B1251 -> 0.10955283 | F79: =Detalle!D1251 -> RECHAZAR | G79: -0.017 | H79: 1439.26 | I79: =IF(Detalle!B1251="","Falta PC real",IF(Detalle!B1251>=Detalle!$G$1,"OK · registrar",IF(Detalle!B1251>=0.2,"Revisar margen","Revisar PC/PV"))) -> Revisar PC/PV
A80: 8657 | B80: C02350 | C80: YANIS DAHIANA JIMENEZ JIMENEZ | D80: Naturgy | E80: =Detalle!B1265 -> 0.13266274 | F80: =Detalle!D1265 -> RECHAZAR | G80: 0.0806 | H80: 4242.23 | I80: =IF(Detalle!B1265="","Falta PC real",IF(Detalle!B1265>=Detalle!$G$1,"OK · registrar",IF(Detalle!B1265>=0.2,"Revisar margen","Revisar PC/PV"))) -> Revisar PC/PV
A81: 8658 | B81: C02380 | C81: FORMATGES MÓNICA | D81: Naturgy | E81: =Detalle!B1279 -> 0.10858512 | F81: =Detalle!D1279 -> RECHAZAR | G81: 0.3502 | H81: 944.84 | I81: =IF(Detalle!B1279="","Falta PC real",IF(Detalle!B1279>=Detalle!$G$1,"OK · registrar",IF(Detalle!B1279>=0.2,"Revisar margen","Revisar PC/PV"))) -> Revisar PC/PV
A82: 8659 | B82: C02400 | C82: MARUJA CHOLBI PUIG | D82: Naturgy | E82: =Detalle!B1293 -> 0.10325051 | F82: =Detalle!D1293 -> RECHAZAR | G82: 0.2926 | H82: 416.78 | I82: =IF(Detalle!B1293="","Falta PC real",IF(Detalle!B1293>=Detalle!$G$1,"OK · registrar",IF(Detalle!B1293>=0.2,"Revisar margen","Revisar PC/PV"))) -> Revisar PC/PV
A83: 8660 | B83: C02420 | C83: KHALID EL JEBLI | D83: Naturgy | E83: =Detalle!B1307 -> 0.17084868 | F83: =Detalle!D1307 -> RECHAZAR | G83: 0.2427 | H83: 1451.67 | I83: =IF(Detalle!B1307="","Falta PC real",IF(Detalle!B1307>=Detalle!$G$1,"OK · registrar",IF(Detalle!B1307>=0.2,"Revisar margen","Revisar PC/PV"))) -> Revisar PC/PV
A84: 8662 | B84: C02470 | C84: TALLER SENDRA CUELLO, S.L. | D84: Naturgy | E84: =Detalle!B1321 -> 0.15848145 | F84: =Detalle!D1321 -> RECHAZAR | G84: 0.2053 | H84: 338.33 | I84: =IF(Detalle!B1321="","Falta PC real",IF(Detalle!B1321>=Detalle!$G$1,"OK · registrar",IF(Detalle!B1321>=0.2,"Revisar margen","Revisar PC/PV"))) -> Revisar PC/PV
A85: 8663 | B85: C02510 | C85: ANTONIO LLIDO ESPASA | D85: Naturgy | E85: =Detalle!B1335 -> 0.08553583 | F85: =Detalle!D1335 -> RECHAZAR | G85: 0.1704 | H85: 233.61 | I85: =IF(Detalle!B1335="","Falta PC real",IF(Detalle!B1335>=Detalle!$G$1,"OK · registrar",IF(Detalle!B1335>=0.2,"Revisar margen","Revisar PC/PV"))) -> Revisar PC/PV
A86: 8665 | B86: C02530 | C86: JUAN SANCHEZ RONDA | D86: Naturgy | E86: =Detalle!B1349 -> 0.093512525 | F86: =Detalle!D1349 -> RECHAZAR | G86: 0.1939 | H86: 274.94 | I86: =IF(Detalle!B1349="","Falta PC real",IF(Detalle!B1349>=Detalle!$G$1,"OK · registrar",IF(Detalle!B1349>=0.2,"Revisar margen","Revisar PC/PV"))) -> Revisar PC/PV
A87: 8666 | B87: C02540 | C87: TERESA MENGUAL ALBEROLA | D87: Naturgy | E87: =Detalle!B1363 -> 0.12167725 | F87: =Detalle!D1363 -> RECHAZAR | G87: 0.2397 | H87: 167.54 | I87: =IF(Detalle!B1363="","Falta PC real",IF(Detalle!B1363>=Detalle!$G$1,"OK · registrar",IF(Detalle!B1363>=0.2,"Revisar margen","Revisar PC/PV"))) -> Revisar PC/PV
A88: 8667 | B88: C02560 | C88: PEDRO IVARS TRO 2018, S.L. | D88: Naturgy | E88: =Detalle!B1377 -> 0.13627977 | F88: =Detalle!D1377 -> RECHAZAR | G88: 0.354 | H88: 452.94 | I88: =IF(Detalle!B1377="","Falta PC real",IF(Detalle!B1377>=Detalle!$G$1,"OK · registrar",IF(Detalle!B1377>=0.2,"Revisar margen","Revisar PC/PV"))) -> Revisar PC/PV
A89: 8670 | B89: C02610 | C89: VEHICULOS ANDRADA, S.L. | D89: Naturgy | E89: =Detalle!B1391 -> 0.148459 | F89: =Detalle!D1391 -> RECHAZAR | G89: 0.28 | H89: 563.43 | I89: =IF(Detalle!B1391="","Falta PC real",IF(Detalle!B1391>=Detalle!$G$1,"OK · registrar",IF(Detalle!B1391>=0.2,"Revisar margen","Revisar PC/PV"))) -> Revisar PC/PV
A90: 8671 | B90: C02630 | C90: AUTOCENTER MARINA ALTA S.L. | D90: Naturgy | E90: =Detalle!B1405 -> 0.13328535 | F90: =Detalle!D1405 -> RECHAZAR | G90: 0.2041 | H90: 145.2 | I90: =IF(Detalle!B1405="","Falta PC real",IF(Detalle!B1405>=Detalle!$G$1,"OK · registrar",IF(Detalle!B1405>=0.2,"Revisar margen","Revisar PC/PV"))) -> Revisar PC/PV
A91: 8672 | B91: C02640 | C91: JUAN CARLOS HERNANDEZ MELERO | D91: Naturgy | E91: =Detalle!B1419 -> 0.14430627 | F91: =Detalle!D1419 -> RECHAZAR | I91: =IF(Detalle!B1419="","Falta PC real",IF(Detalle!B1419>=Detalle!$G$1,"OK · registrar",IF(Detalle!B1419>=0.2,"Revisar margen","Revisar PC/PV"))) -> Revisar PC/PV
A92: 8674 | B92: C02680 | C92: ALVARO DAVID OCHOA BIOSCA | D92: Naturgy | E92: =Detalle!B1433 -> 0.15852433 | F92: =Detalle!D1433 -> RECHAZAR | G92: 1 | H92: 2.65 | I92: =IF(Detalle!B1433="","Falta PC real",IF(Detalle!B1433>=Detalle!$G$1,"OK · registrar",IF(Detalle!B1433>=0.2,"Revisar margen","Revisar PC/PV"))) -> Revisar PC/PV
A93: 8676 | B93: C02710 | C93: CASA LILI S.L. AUTOS (EXPOSICIÓN) | D93: Naturgy | E93: =Detalle!B1447 -> 0.16525708 | F93: =Detalle!D1447 -> RECHAZAR | G93: 1 | H93: 3.77 | I93: =IF(Detalle!B1447="","Falta PC real",IF(Detalle!B1447>=Detalle!$G$1,"OK · registrar",IF(Detalle!B1447>=0.2,"Revisar margen","Revisar PC/PV"))) -> Revisar PC/PV
A94: 8677 | B94: C02740 | C94: FRANCISCO DANIEL GUIJARRO ORTEGA | D94: Naturgy | E94: =Detalle!B1461 -> 0.20549393 | F94: =Detalle!D1461 -> REVISAR | G94: 1 | H94: 3.17 | I94: =IF(Detalle!B1461="","Falta PC real",IF(Detalle!B1461>=Detalle!$G$1,"OK · registrar",IF(Detalle!B1461>=0.2,"Revisar margen","Revisar PC/PV"))) -> Revisar margen
A95: 8678 | B95: C02760 | C95: ISABEL RAMIREZ CAPDEVILA | D95: Naturgy | E95: =Detalle!B1475 -> 0.19502711 | F95: =Detalle!D1475 -> RECHAZAR | G95: 1 | H95: 3.07 | I95: =IF(Detalle!B1475="","Falta PC real",IF(Detalle!B1475>=Detalle!$G$1,"OK · registrar",IF(Detalle!B1475>=0.2,"Revisar margen","Revisar PC/PV"))) -> Revisar PC/PV
A96: 8679 | B96: C02780 | C96: MARIA PILAR CATALA SANTAMARIA | D96: Naturgy | E96: =Detalle!B1489 -> 0.14012933 | F96: =Detalle!D1489 -> RECHAZAR | G96: 1 | H96: 3.15 | I96: =IF(Detalle!B1489="","Falta PC real",IF(Detalle!B1489>=Detalle!$G$1,"OK · registrar",IF(Detalle!B1489>=0.2,"Revisar margen","Revisar PC/PV"))) -> Revisar PC/PV
A97: 8680 | B97: C02800 | C97: ABDESLAM LAMRANI | D97: Iberdrola | E97: =Detalle!B1503 -> -0.044478508 | F97: =Detalle!D1503 -> RECHAZAR | I97: =IF(Detalle!B1503="","Falta PC real",IF(Detalle!B1503>=Detalle!$G$1,"OK · registrar",IF(Detalle!B1503>=0.2,"Revisar margen","Revisar PC/PV"))) -> Revisar PC/PV
A98: 8681 | B98: C02820 | C98: FRANCISCO DANIEL GUIJARRO ORTEGA | D98: Iberdrola | E98: =Detalle!B1517 -> -0.091232328 | F98: =Detalle!D1517 -> RECHAZAR | G98: 1 | H98: 1.22 | I98: =IF(Detalle!B1517="","Falta PC real",IF(Detalle!B1517>=Detalle!$G$1,"OK · registrar",IF(Detalle!B1517>=0.2,"Revisar margen","Revisar PC/PV"))) -> Revisar PC/PV
A99: 8682 | B99: C02840 | C99: VICENTE BAS ALENTADO | D99: Naturgy | E99: =Detalle!B1531 -> 0.19200776 | F99: =Detalle!D1531 -> RECHAZAR | G99: 1 | H99: 3.47 | I99: =IF(Detalle!B1531="","Falta PC real",IF(Detalle!B1531>=Detalle!$G$1,"OK · registrar",IF(Detalle!B1531>=0.2,"Revisar margen","Revisar PC/PV"))) -> Revisar PC/PV
A100: 8683 | B100: C02860 | C100: SALVADOR TORRES BISQUERT | D100: Naturgy | E100: =Detalle!B1545 -> 0.20981103 | F100: =Detalle!D1545 -> REVISAR | G100: 1 | H100: 3.75 | I100: =IF(Detalle!B1545="","Falta PC real",IF(Detalle!B1545>=Detalle!$G$1,"OK · registrar",IF(Detalle!B1545>=0.2,"Revisar margen","Revisar PC/PV"))) -> Revisar margen
A101: 8685 | B101: C02920 | C101: JAKUB JAN PICHOLA | D101: Naturgy | E101: =Detalle!B1559 -> 0.09370139 | F101: =Detalle!D1559 -> RECHAZAR | G101: 1 | H101: 1.24 | I101: =IF(Detalle!B1559="","Falta PC real",IF(Detalle!B1559>=Detalle!$G$1,"OK · registrar",IF(Detalle!B1559>=0.2,"Revisar margen","Revisar PC/PV"))) -> Revisar PC/PV
...

Sheet Detalle
A1: VALIDACIÓN FACTURAS 2.0TD · abril 2026 · margen objetivo ▶ | G1: 0.3 | H1: APROBAR ≥ objetivo · REVISAR 20–30% · RECHAZAR <20% | PC ámbar = provisional, editable
A3: Factura 8550 · C02150 · FUNDACIÓN FSU PROGRAMAS INTERNACIONALES | H3: ES0021000020111640FT · Naturgy · 01/04/26 a 30/04/26 | P3: HISTÓRICO DEL CUPS · HOJA TTVA LUZ
A4: Concepto | B4: PENDIENTE (sin registrar) | H4: MES ANTERIOR · Fact.6304 | L4: AÑO ANTERIOR · Fact.4583 | P4: Cobrado total: 2.436 €
B5: Cant | C5: Días | D5: PC real | E5: PV | F5: Importe | H5: Cant | I5: PV | J5: Importe | L5: Cant | M5: PV | N5: Importe | P5: Pagado total: 1.753 €
A6: P1 Potencia | B6: 10.392 | C6: 30 | D6: 3.68919 | E6: 4.82 | F6: =ROUND(B6*E6,2) -> 50.09 | H6: 10.392 | I6: 4.82 | J6: =ROUND(H6*I6,2) -> 50.09 | L6: 10.392 | M6: 4.82 | N6: =ROUND(L6*M6,2) -> 50.09 | P6: DIF: 682 € · Margen hist.: 28.0%
A7: P2 Potencia | B7: 10.392 | C7: 30 | D7: 1.31928 | E7: 2.37 | F7: =ROUND(B7*E7,2) -> 24.63 | H7: 10.392 | I7: 2.37 | J7: =ROUND(H7*I7,2) -> 24.63 | L7: 10.392 | M7: 2.37 | N7: =ROUND(L7*M7,2) -> 24.63 | P7: Importe mensual cobrado (€) · 24 meses ▾
A8: P1 Energía | B8: 195.263 | C8: 30 | D8: 0.111171 | E8: 0.17 | F8: =ROUND(B8*E8,2) -> 33.19 | H8: 477.269 | I8: 0.175 | J8: =ROUND(H8*I8,2) -> 83.52 | L8: 95.263 | M8: 0.175 | N8: =ROUND(L8*M8,2) -> 16.67 | P8: Peor mes: 2024-08 · 66 €
A9: P2 Energía | B9: 199.672 | C9: 30 | D9: 0.111171 | E9: 0.17 | F9: =ROUND(B9*E9,2) -> 33.94 | H9: 460.686 | I9: 0.175 | J9: =ROUND(H9*I9,2) -> 80.62 | L9: 99.672 | M9: 0.175 | N9: =ROUND(L9*M9,2) -> 17.44
A10: P3 Energía | B10: 270.288 | C10: 30 | D10: 0.111171 | E10: 0.17 | F10: =ROUND(B10*E10,2) -> 45.95 | H10: 525.938 | I10: 0.175 | J10: =ROUND(H10*I10,2) -> 92.04 | L10: 170.288 | M10: 0.175 | N10: =ROUND(L10*M10,2) -> 29.8
A11: Alquiler contador | B11: 1 | C11: 30 | D11: 1.3414 | E11: 1 | F11: =ROUND(B11*E11,2) -> 1 | H11: 1 | I11: 1 | J11: =ROUND(H11*I11,2) -> 1 | L11: 1 | M11: 1 | N11: =ROUND(L11*M11,2) -> 1
A12: Bono social | B12: 30 | C12: 30 | D12: 0.5736 | E12: 0.01274 | F12: =ROUND(B12*E12,2) -> 0.38 | H12: 30 | I12: 0.01274 | J12: =ROUND(H12*I12,2) -> 0.38 | L12: 30 | M12: 0.00685 | N12: =ROUND(L12*M12,2) -> 0.21
A13: Tasa eléctrica | B13: 10.03 | C13: 30 | D13: 0.27312 | E13: 1 | F13: =ROUND(B13*E13,2) -> 10.03 | H13: 17.16 | I13: 1 | J13: =ROUND(H13*I13,2) -> 17.16 | L13: 7.09 | M13: 1 | N13: =ROUND(L13*M13,2) -> 7.09
A14: TOTAL c/IVA | F14: =ROUND((SUM(F6:F13)-F13)*1.1+F13,2) -> 218.13 | J14: =ROUND(SUM(J6:J13),2) -> 349.44 | N14: =ROUND(SUM(N6:N13),2) -> 146.93
A15: MARGEN sin registrar | B15: =IF((F8+F6+F10+F7+F9)=0,"",((F8+F6+F10+F7+F9)-(B8*D8+B6*D6+B10*D10+B7*D7+B9*D9))/(F8+F6+F10+F7+F9)) -> 0.32906535 | D15: =IF(B15="","SIN PC",IF(B15>=Detalle!$G$1,"APROBAR",IF(B15>=0.2,"REVISAR","RECHAZAR"))) -> APROBAR
A17: Factura 8551 · C02140 · FUNDACIÓN FSU PROGRAMAS INTERNACIONALES | H17: ES0021000008997145KW · Naturgy · 01/04/26 a 30/04/26 | P17: HISTÓRICO DEL CUPS · HOJA TTVA LUZ
A18: Concepto | B18: PENDIENTE (sin registrar) | H18: MES ANTERIOR · Fact.6308 | L18: AÑO ANTERIOR · Fact.4584 | P18: Cobrado total: 2.120 €
B19: Cant | C19: Días | D19: PC real | E19: PV | F19: Importe | H19: Cant | I19: PV | J19: Importe | L19: Cant | M19: PV | N19: Importe | P19: Pagado total: 1.617 €
A20: P1 Potencia | B20: 10.392 | C20: 30 | D20: 3.68919 | E20: 4.82 | F20: =ROUND(B20*E20,2) -> 50.09 | H20: 10.392 | I20: 4.82 | J20: =ROUND(H20*I20,2) -> 50.09 | L20: 10.392 | M20: 4.82 | N20: =ROUND(L20*M20,2) -> 50.09 | P20: DIF: 503 € · Margen hist.: 23.7%
A21: P2 Potencia | B21: 10.392 | C21: 30 | D21: 1.31928 | E21: 2.37 | F21: =ROUND(B21*E21,2) -> 24.63 | H21: 10.392 | I21: 2.37 | J21: =ROUND(H21*I21,2) -> 24.63 | L21: 10.392 | M21: 2.37 | N21: =ROUND(L21*M21,2) -> 24.63 | P21: Importe mensual cobrado (€) · 24 meses ▾
A22: P1 Energía | B22: 177.5 | C22: 30 | D22: 0.111171 | E22: 0.17 | F22: =ROUND(B22*E22,2) -> 30.18 | H22: 309.614 | I22: 0.175 | J22: =ROUND(H22*I22,2) -> 54.18 | L22: 77.5 | M22: 0.175 | N22: =ROUND(L22*M22,2) -> 13.56 | P22: Peor mes: 2024-08 · 84 €
A23: P2 Energía | B23: 168.86 | C23: 30 | D23: 0.111171 | E23: 0.17 | F23: =ROUND(B23*E23,2) -> 28.71 | H23: 186.461 | I23: 0.175 | J23: =ROUND(H23*I23,2) -> 32.63 | L23: 68.86 | M23: 0.175 | N23: =ROUND(L23*M23,2) -> 12.05
A24: P3 Energía | B24: 246.145 | C24: 30 | D24: 0.111171 | E24: 0.17 | F24: =ROUND(B24*E24,2) -> 41.84 | H24: 355.272 | I24: 0.175 | J24: =ROUND(H24*I24,2) -> 62.17 | L24: 146.145 | M24: 0.175 | N24: =ROUND(L24*M24,2) -> 25.58
A25: Alquiler contador | B25: 1 | C25: 30 | D25: 1.3414 | E25: 1 | F25: =ROUND(B25*E25,2) -> 1 | H25: 1 | I25: 1 | J25: =ROUND(H25*I25,2) -> 1 | L25: 1 | M25: 1 | N25: =ROUND(L25*M25,2) -> 1
A26: Bono social | B26: 30 | C26: 30 | D26: 0.5736 | E26: 0.01274 | F26: =ROUND(B26*E26,2) -> 0.38 | H26: 30 | I26: 0.01274 | J26: =ROUND(H26*I26,2) -> 0.38 | L26: 30 | M26: 0.00685 | N26: =ROUND(L26*M26,2) -> 0.21
A27: Tasa eléctrica | B27: 9.37 | C27: 30 | D27: 0.27312 | E27: 1 | F27: =ROUND(B27*E27,2) -> 9.37 | H27: 12.1 | I27: 1 | J27: =ROUND(H27*I27,2) -> 12.1 | L27: 6.44 | M27: 1 | N27: =ROUND(L27*M27,2) -> 6.44
A28: TOTAL c/IVA | F28: =ROUND((SUM(F20:F27)-F27)*1.1+F27,2) -> 203.88 | J28: =ROUND(SUM(J20:J27),2) -> 237.18 | N28: =ROUND(SUM(N20:N27),2) -> 133.56
A29: MARGEN sin registrar | B29: =IF((F22+F20+F24+F21+F23)=0,"",((F22+F20+F24+F21+F23)-(B22*D22+B20*D20+B24*D24+B21*D21+B23*D23))/(F22+F20+F24+F21+F23)) -> 0.32791454 | D29: =IF(B29="","SIN PC",IF(B29>=Detalle!$G$1,"APROBAR",IF(B29>=0.2,"REVISAR","RECHAZAR"))) -> APROBAR
A31: Factura 8552 · C02130 · FUNDACIÓN FSU PROGRAMAS INTERNACIONALES | H31: ES0021000012268833JD · Naturgy · 01/04/26 a 30/04/26 | P31: HISTÓRICO DEL CUPS · HOJA TTVA LUZ
A32: Concepto | B32: PENDIENTE (sin registrar) | H32: MES ANTERIOR · Fact.6311 | L32: AÑO ANTERIOR · Fact.4585 | P32: Cobrado total: 3.194 €
B33: Cant | C33: Días | D33: PC real | E33: PV | F33: Importe | H33: Cant | I33: PV | J33: Importe | L33: Cant | M33: PV | N33: Importe | P33: Pagado total: 2.235 €
A34: P1 Potencia | B34: 6.928 | C34: 30 | D34: 3.68919 | E34: 4.82 | F34: =ROUND(B34*E34,2) -> 33.39 | H34: 6.928 | I34: 4.82 | J34: =ROUND(H34*I34,2) -> 33.39 | L34: 6.928 | M34: 4.82 | N34: =ROUND(L34*M34,2) -> 33.39 | P34: DIF: 960 € · Margen hist.: 30.0%
A35: P2 Potencia | B35: 6.928 | C35: 30 | D35: 1.31928 | E35: 2.37 | F35: =ROUND(B35*E35,2) -> 16.42 | H35: 6.928 | I35: 2.37 | J35: =ROUND(H35*I35,2) -> 16.42 | L35: 6.928 | M35: 2.37 | N35: =ROUND(L35*M35,2) -> 16.42 | P35: Importe mensual cobrado (€) · 24 meses ▾
A36: P1 Energía | B36: 301.884 | C36: 30 | D36: 0.111171 | E36: 0.17 | F36: =ROUND(B36*E36,2) -> 51.32 | H36: 250.417 | I36: 0.175 | J36: =ROUND(H36*I36,2) -> 43.82 | L36: 201.884 | M36: 0.175 | N36: =ROUND(L36*M36,2) -> 35.33 | P36: Peor mes: 2024-08 · 129 €
A37: P2 Energía | B37: 374.313 | C37: 30 | D37: 0.111171 | E37: 0.17 | F37: =ROUND(B37*E37,2) -> 63.63 | H37: 234.006 | I37: 0.175 | J37: =ROUND(H37*I37,2) -> 40.95 | L37: 174.313 | M37: 0.175 | N37: =ROUND(L37*M37,2) -> 30.5
A38: P3 Energía | B38: 542.307 | C38: 30 | D38: 0.111171 | E38: 0.17 | F38: =ROUND(B38*E38,2) -> 92.19 | H38: 376.925 | I38: 0.175 | J38: =ROUND(H38*I38,2) -> 65.96 | L38: 342.307 | M38: 0.175 | N38: =ROUND(L38*M38,2) -> 59.9
A39: Alquiler contador | B39: 1 | C39: 30 | D39: 1.3414 | E39: 1 | F39: =ROUND(B39*E39,2) -> 1 | H39: 1 | I39: 1 | J39: =ROUND(H39*I39,2) -> 1 | L39: 1 | M39: 1 | N39: =ROUND(L39*M39,2) -> 1
A40: Bono social | B40: 30 | C40: 30 | D40: 0.5736 | E40: 0.01274 | F40: =ROUND(B40*E40,2) -> 0.38 | H40: 30 | I40: 0.01274 | J40: =ROUND(H40*I40,2) -> 0.38 | L40: 30 | M40: 0.00685 | N40: =ROUND(L40*M40,2) -> 0.21
A41: Tasa eléctrica | B41: 13.65 | C41: 30 | D41: 0.27312 | E41: 1 | F41: =ROUND(B41*E41,2) -> 13.65 | H41: 12.86 | I41: 1 | J41: =ROUND(H41*I41,2) -> 12.86 | L41: 8.83 | M41: 1 | N41: =ROUND(L41*M41,2) -> 8.83
A42: TOTAL c/IVA | F42: =ROUND((SUM(F34:F41)-F41)*1.1+F41,2) -> 297.81 | J42: =ROUND(SUM(J34:J41),2) -> 214.78 | N42: =ROUND(SUM(N34:N41),2) -> 185.58
A43: MARGEN sin registrar | B43: =IF((F36+F34+F38+F35+F37)=0,"",((F36+F34+F38+F35+F37)-(B36*D36+B34*D34+B38*D38+B35*D35+B37*D37))/(F36+F34+F38+F35+F37)) -> 0.33776615 | D43: =IF(B43="","SIN PC",IF(B43>=Detalle!$G$1,"APROBAR",IF(B43>=0.2,"REVISAR","RECHAZAR"))) -> APROBAR
A45: Factura 8553 · C02120 · FUNDACIÓN FSU PROGRAMAS INTERNACIONALES | H45: ES0021000012268831JF · Naturgy · 01/04/26 a 30/04/26 | P45: HISTÓRICO DEL CUPS · HOJA TTVA LUZ
A46: Concepto | B46: PENDIENTE (sin registrar) | H46: MES ANTERIOR · Fact.6314 | L46: AÑO ANTERIOR · Fact.4586 | P46: Cobrado total: 2.606 €
B47: Cant | C47: Días | D47: PC real | E47: PV | F47: Importe | H47: Cant | I47: PV | J47: Importe | L47: Cant | M47: PV | N47: Importe | P47: Pagado total: 1.842 €
A48: P1 Potencia | B48: 6.928 | C48: 30 | D48: 3.68919 | E48: 4.82 | F48: =ROUND(B48*E48,2) -> 33.39 | H48: 6.928 | I48: 4.82 | J48: =ROUND(H48*I48,2) -> 33.39 | L48: 6.928 | M48: 4.82 | N48: =ROUND(L48*M48,2) -> 33.39 | P48: DIF: 764 € · Margen hist.: 29.3%
A49: P2 Potencia | B49: 6.928 | C49: 30 | D49: 1.31928 | E49: 2.37 | F49: =ROUND(B49*E49,2) -> 16.42 | H49: 6.928 | I49: 2.37 | J49: =ROUND(H49*I49,2) -> 16.42 | L49: 6.928 | M49: 2.37 | N49: =ROUND(L49*M49,2) -> 16.42 | P49: Importe mensual cobrado (€) · 24 meses ▾
A50: P1 Energía | B50: 373.974 | C50: 30 | D50: 0.142913 | E50: 0.17 | F50: =ROUND(B50*E50,2) -> 63.58 | H50: 258.447 | I50: 0.175 | J50: =ROUND(H50*I50,2) -> 45.23 | L50: 173.974 | M50: 0.175 | N50: =ROUND(L50*M50,2) -> 30.45 | P50: Peor mes: 2024-08 · 116 €
A51: P2 Energía | B51: 356.102 | C51: 30 | D51: 0.142913 | E51: 0.17 | F51: =ROUND(B51*E51,2) -> 60.54 | H51: 239.045 | I51: 0.175 | J51: =ROUND(H51*I51,2) -> 41.83 | L51: 156.102 | M51: 0.175 | N51: =ROUND(L51*M51,2) -> 27.32
A52: P3 Energía | B52: 530.705 | C52: 30 | D52: 0.142913 | E52: 0.17 | F52: =ROUND(B52*E52,2) -> 90.22 | H52: 473.601 | I52: 0.175 | J52: =ROUND(H52*I52,2) -> 82.88 | L52: 330.705 | M52: 0.175 | N52: =ROUND(L52*M52,2) -> 57.87
A53: Alquiler contador | B53: 1 | C53: 30 | D53: 1.3414 | E53: 1 | F53: =ROUND(B53*E53,2) -> 1 | H53: 1 | I53: 1 | J53: =ROUND(H53*I53,2) -> 1 | L53: 1 | M53: 1 | N53: =ROUND(L53*M53,2) -> 1
A54: Bono social | B54: 30 | C54: 30 | D54: 0.5736 | E54: 0.01274 | F54: =ROUND(B54*E54,2) -> 0.38 | H54: 30 | I54: 0.00685 | J54: =ROUND(H54*I54,2) -> 0.21 | L54: 30 | M54: 0.00685 | N54: =ROUND(L54*M54,2) -> 0.21
A55: Tasa eléctrica | B55: 14.01 | C55: 30 | D55: 0.27799 | E55: 1 | F55: =ROUND(B55*E55,2) -> 14.01 | H55: 11.67 | I55: 1 | J55: =ROUND(H55*I55,2) -> 11.67 | L55: 8.46 | M55: 1 | N55: =ROUND(L55*M55,2) -> 8.46
A56: TOTAL c/IVA | F56: =ROUND((SUM(F48:F55)-F55)*1.1+F55,2) -> 306.09 | J56: =ROUND(SUM(J48:J55),2) -> 232.63 | N56: =ROUND(SUM(N48:N55),2) -> 175.12
A57: MARGEN sin registrar | B57: =IF((F50+F48+F52+F49+F51)=0,"",((F50+F48+F52+F49+F51)-(B50*D50+B48*D48+B52*D52+B49*D49+B51*D51))/(F50+F48+F52+F49+F51)) -> 0.18652025 | D57: =IF(B57="","SIN PC",IF(B57>=Detalle!$G$1,"APROBAR",IF(B57>=0.2,"REVISAR","RECHAZAR"))) -> RECHAZAR
A59: Factura 8554 · C02110 · FUNDACIÓN FSU PROGRAMAS INTERNACIONALES | H59: ES0021000012268829JM · Naturgy · 01/04/26 a 30/04/26 | P59: HISTÓRICO DEL CUPS · HOJA TTVA LUZ
A60: Concepto | B60: PENDIENTE (sin registrar) | H60: MES ANTERIOR · Fact.6312 | L60: AÑO ANTERIOR · Fact.4587 | P60: Cobrado total: 5.249 €
B61: Cant | C61: Días | D61: PC real | E61: PV | F61: Importe | H61: Cant | I61: PV | J61: Importe | L61: Cant | M61: PV | N61: Importe | P61: Pagado total: 3.622 €
A62: P1 Potencia | B62: 6.928 | C62: 30 | D62: 3.68919 | E62: 4.82 | F62: =ROUND(B62*E62,2) -> 33.39 | H62: 6.928 | I62: 4.82 | J62: =ROUND(H62*I62,2) -> 33.39 | L62: 6.928 | M62: 4.82 | N62: =ROUND(L62*M62,2) -> 33.39 | P62: DIF: 1.627 € · Margen hist.: 31.0%
A63: P2 Potencia | B63: 6.928 | C63: 30 | D63: 1.31928 | E63: 2.37 | F63: =ROUND(B63*E63,2) -> 16.42 | H63: 6.928 | I63: 2.37 | J63: =ROUND(H63*I63,2) -> 16.42 | L63: 6.928 | M63: 2.37 | N63: =ROUND(L63*M63,2) -> 16.42 | P63: Importe mensual cobrado (€) · 24 meses ▾
A64: P1 Energía | B64: 425.199 | C64: 30 | D64: 0.111171 | E64: 0.17 | F64: =ROUND(B64*E64,2) -> 72.28 | H64: 254.599 | I64: 0.1724 | J64: =ROUND(H64*I64,2) -> 43.89 | L64: 225.199 | M64: 0.175 | N64: =ROUND(L64*M64,2) -> 39.41 | P64: Peor mes: 2024-11 · 187 €
A65: P2 Energía | B65: 407.266 | C65: 30 | D65: 0.111171 | E65: 0.17 | F65: =ROUND(B65*E65,2) -> 69.24 | H65: 235.376 | I65: 0.1724 | J65: =ROUND(H65*I65,2) -> 40.58 | L65: 207.266 | M65: 0.175 | N65: =ROUND(L65*M65,2) -> 36.27
A66: P3 Energía | B66: 606.93 | C66: 30 | D66: 0.111171 | E66: 0.17 | F66: =ROUND(B66*E66,2) -> 103.18 | H66: 414.585 | I66: 0.1724 | J66: =ROUND(H66*I66,2) -> 71.47 | L66: 406.93 | M66: 0.175 | N66: =ROUND(L66*M66,2) -> 71.21
A67: Alquiler contador | B67: 1 | C67: 30 | D67: 1.3414 | E67: 1 | F67: =ROUND(B67*E67,2) -> 1 | H67: 1 | I67: 1 | J67: =ROUND(H67*I67,2) -> 1 | L67: 1 | M67: 1 | N67: =ROUND(L67*M67,2) -> 1
A68: Bono social | B68: 30 | C68: 30 | D68: 0.5736 | E68: 0.01274 | F68: =ROUND(B68*E68,2) -> 0.38 | H68: 30 | I68: 0.01274 | J68: =ROUND(H68*I68,2) -> 0.38 | L68: 30 | M68: 0.00685 | N68: =ROUND(L68*M68,2) -> 0.21
A69: Tasa eléctrica | B69: 15.66 | C69: 30 | D69: 0.27312 | E69: 1 | F69: =ROUND(B69*E69,2) -> 15.66 | H69: 10.98 | I69: 1 | J69: =ROUND(H69*I69,2) -> 10.98 | L69: 10.57 | M69: 1 | N69: =ROUND(L69*M69,2) -> 10.57
A70: TOTAL c/IVA | F70: =ROUND((SUM(F62:F69)-F69)*1.1+F69,2) -> 341.14 | J70: =ROUND(SUM(J62:J69),2) -> 218.11 | N70: =ROUND(SUM(N62:N69),2) -> 208.48
A71: MARGEN sin registrar | B71: =IF((F64+F62+F66+F63+F65)=0,"",((F64+F62+F66+F63+F65)-(B64*D64+B62*D62+B66*D66+B63*D63+B65*D65))/(F64+F62+F66+F63+F65)) -> 0.33884194 | D71: =IF(B71="","SIN PC",IF(B71>=Detalle!$G$1,"APROBAR",IF(B71>=0.2,"REVISAR","RECHAZAR"))) -> APROBAR
A73: Factura 8555 · C02100 · FUNDACIÓN FSU PROGRAMAS INTERNACIONALES | H73: ES0021000012268826JW · Naturgy · 01/04/26 a 30/04/26 | P73: HISTÓRICO DEL CUPS · HOJA TTVA LUZ
A74: Concepto | B74: PENDIENTE (sin registrar) | H74: MES ANTERIOR · Fact.6313 | L74: AÑO ANTERIOR · Fact.4588 | P74: Cobrado total: 1.842 €
B75: Cant | C75: Días | D75: PC real | E75: PV | F75: Importe | H75: Cant | I75: PV | J75: Importe | L75: Cant | M75: PV | N75: Importe | P75: Pagado total: 1.285 €
A76: P1 Potencia | B76: 6.928 | C76: 30 | D76: 3.68919 | E76: 4.82 | F76: =ROUND(B76*E76,2) -> 33.39 | H76: 6.928 | I76: 4.82 | J76: =ROUND(H76*I76,2) -> 33.39 | L76: 6.928 | M76: 4.82 | N76: =ROUND(L76*M76,2) -> 33.39 | P76: DIF: 557 € · Margen hist.: 30.2%
A77: P2 Potencia | B77: 6.928 | C77: 30 | D77: 1.31928 | E77: 2.37 | F77: =ROUND(B77*E77,2) -> 16.42 | H77: 6.928 | I77: 2.37 | J77: =ROUND(H77*I77,2) -> 16.42 | L77: 6.928 | M77: 2.37 | N77: =ROUND(L77*M77,2) -> 16.42 | P77: Importe mensual cobrado (€) · 24 meses ▾
A78: P1 Energía | B78: 191.223 | C78: 30 | D78: 0.111171 | E78: 0.1724 | F78: =ROUND(B78*E78,2) -> 32.97 | H78: 241.525 | I78: 0.1724 | J78: =ROUND(H78*I78,2) -> 41.64 | L78: 98.223 | M78: 0.175 | N78: =ROUND(L78*M78,2) -> 17.19 | P78: Peor mes: 2024-11 · 76 €
A79: P2 Energía | B79: 176.381 | C79: 30 | D79: 0.111171 | E79: 0.1724 | F79: =ROUND(B79*E79,2) -> 30.41 | H79: 215.785 | I79: 0.1724 | J79: =ROUND(H79*I79,2) -> 37.2 | L79: 75.381 | M79: 0.175 | N79: =ROUND(L79*M79,2) -> 13.19
A80: P3 Energía | B80: 242.943 | C80: 30 | D80: 0.111171 | E80: 0.17 | F80: =ROUND(B80*E80,2) -> 41.3 | H80: 326.045 | I80: 0.1724 | J80: =ROUND(H80*I80,2) -> 56.21 | L80: 142.943 | M80: 0.175 | N80: =ROUND(L80*M80,2) -> 25.02
A81: Alquiler contador | B81: 1 | C81: 30 | D81: 1.3414 | E81: 1 | F81: =ROUND(B81*E81,2) -> 1 | H81: 1 | I81: 1 | J81: =ROUND(H81*I81,2) -> 1 | L81: 1 | M81: 1 | N81: =ROUND(L81*M81,2) -> 1
A82: Bono social | B82: 30 | C82: 30 | D82: 0.5736 | E82: 0.01274 | F82: =ROUND(B82*E82,2) -> 0.38 | H82: 30 | I82: 0.01274 | J82: =ROUND(H82*I82,2) -> 0.38 | L82: 30 | M82: 0.00685 | N82: =ROUND(L82*M82,2) -> 0.21
A83: Tasa eléctrica | B83: 8.24 | C83: 30 | D83: 0.27312 | E83: 1 | F83: =ROUND(B83*E83,2) -> 8.24 | H83: 9.86 | I83: 1 | J83: =ROUND(H83*I83,2) -> 9.86 | L83: 5.39 | M83: 1 | N83: =ROUND(L83*M83,2) -> 5.39
A84: TOTAL c/IVA | F84: =ROUND((SUM(F76:F83)-F83)*1.1+F83,2) -> 179.7 | J84: =ROUND(SUM(J76:J83),2) -> 196.1 | N84: =ROUND(SUM(N76:N83),2) -> 111.81
A85: MARGEN sin registrar | B85: =IF((F78+F76+F80+F77+F79)=0,"",((F78+F76+F80+F77+F79)-(B78*D78+B76*D76+B80*D80+B77*D77+B79*D79))/(F78+F76+F80+F77+F79)) -> 0.33604893 | D85: =IF(B85="","SIN PC",IF(B85>=Detalle!$G$1,"APROBAR",IF(B85>=0.2,"REVISAR","RECHAZAR"))) -> APROBAR
A87: Factura 8556 · C02090 · FUNDACIÓN FSU PROGRAMAS INTERNACIONALES | H87: ES0021000012268828JG · Naturgy · 01/04/26 a 30/04/26 | P87: HISTÓRICO DEL CUPS · HOJA TTVA LUZ
A88: Concepto | B88: PENDIENTE (sin registrar) | H88: MES ANTERIOR · Fact.6306 | L88: AÑO ANTERIOR · Fact.4589 | P88: Cobrado total: 2.954 €
B89: Cant | C89: Días | D89: PC real | E89: PV | F89: Importe | H89: Cant | I89: PV | J89: Importe | L89: Cant | M89: PV | N89: Importe | P89: Pagado total: 2.099 €
A90: P1 Potencia | B90: 6.928 | C90: 30 | D90: 3.68919 | E90: 4.82 | F90: =ROUND(B90*E90,2) -> 33.39 | H90: 6.928 | I90: 4.82 | J90: =ROUND(H90*I90,2) -> 33.39 | L90: 6.928 | M90: 4.82 | N90: =ROUND(L90*M90,2) -> 33.39 | P90: DIF: 855 € · Margen hist.: 28.9%
A91: P2 Potencia | B91: 6.928 | C91: 30 | D91: 1.31928 | E91: 2.37 | F91: =ROUND(B91*E91,2) -> 16.42 | H91: 6.928 | I91: 2.37 | J91: =ROUND(H91*I91,2) -> 16.42 | L91: 6.928 | M91: 2.37 | N91: =ROUND(L91*M91,2) -> 16.42 | P91: Importe mensual cobrado (€) · 24 meses ▾
A92: P1 Energía | B92: 374.461 | C92: 30 | D92: 0.111171 | E92: 0.17 | F92: =ROUND(B92*E92,2) -> 63.66 | H92: 372.052 | I92: 0.175 | J92: =ROUND(H92*I92,2) -> 65.11 | L92: 284.461 | M92: 0.175 | N92: =ROUND(L92*M92,2) -> 49.78 | P92: Peor mes: 2024-11 · 92 €
A93: P2 Energía | B93: 399.208 | C93: 30 | D93: 0.111171 | E93: 0.17 | F93: =ROUND(B93*E93,2) -> 67.87 | H93: 370.213 | I93: 0.175 | J93: =ROUND(H93*I93,2) -> 64.79 | L93: 259.208 | M93: 0.175 | N93: =ROUND(L93*M93,2) -> 45.36
A94: P3 Energía | B94: 681.209 | C94: 30 | D94: 0.111171 | E94: 0.17 | F94: =ROUND(B94*E94,2) -> 115.81 | H94: 657.524 | I94: 0.175 | J94: =ROUND(H94*I94,2) -> 115.07 | L94: 485.209 | M94: 0.175 | N94: =ROUND(L94*M94,2) -> 84.91
A95: Alquiler contador | B95: 1 | C95: 30 | D95: 1.3414 | E95: 1 | F95: =ROUND(B95*E95,2) -> 1 | H95: 1 | I95: 1 | J95: =ROUND(H95*I95,2) -> 1 | L95: 1 | M95: 1 | N95: =ROUND(L95*M95,2) -> 1
A96: Bono social | B96: 30 | C96: 30 | D96: 0.5736 | E96: 0.01274 | F96: =ROUND(B96*E96,2) -> 0.38 | H96: 30 | I96: 0.01274 | J96: =ROUND(H96*I96,2) -> 0.38 | L96: 30 | M96: 0.00685 | N96: =ROUND(L96*M96,2) -> 0.21
A97: Tasa eléctrica | B97: 15.86 | C97: 30 | D97: 0.27312 | E97: 1 | F97: =ROUND(B97*E97,2) -> 15.86 | H97: 15.75 | I97: 1 | J97: =ROUND(H97*I97,2) -> 15.75 | L97: 11.76 | M97: 1 | N97: =ROUND(L97*M97,2) -> 11.76
A98: TOTAL c/IVA | F98: =ROUND((SUM(F90:F97)-F97)*1.1+F97,2) -> 344.24 | J98: =ROUND(SUM(J90:J97),2) -> 311.91 | N98: =ROUND(SUM(N90:N97),2) -> 242.83
A99: MARGEN sin registrar | B99: =IF((F92+F90+F94+F91+F93)=0,"",((F92+F90+F94+F91+F93)-(B92*D92+B90*D90+B94*D94+B91*D91+B93*D93))/(F92+F90+F94+F91+F93)) -> 0.33892336 | D99: =IF(B99="","SIN PC",IF(B99>=Detalle!$G$1,"APROBAR",IF(B99>=0.2,"REVISAR","RECHAZAR"))) -> APROBAR
A101: Factura 8557 · C02080 · FUNDACIÓN FSU PROGRAMAS INTERNACIONALES | H101: ES0021000012268825JR · Naturgy · 01/04/26 a 30/04/26 | P101: HISTÓRICO DEL CUPS · HOJA TTVA LUZ
A102: Concepto | B102: PENDIENTE (sin registrar) | H102: MES ANTERIOR · Fact.6303 | L102: AÑO ANTERIOR · Fact.4590
B103: Cant | C103: Días | D103: PC real | E103: PV | F103: Importe | H103: Cant | I103: PV | J103: Importe | L103: Cant | M103: PV | N103: Importe
A104: P1 Potencia | B104: 6.928 | C104: 30 | D104: 3.68919 | E104: 4.82 | F104: =ROUND(B104*E104,2) -> 33.39 | H104: 6.928 | I104: 4.82 | J104: =ROUND(H104*I104,2) -> 33.39 | L104: 6.928 | M104: 4.82 | N104: =ROUND(L104*M104,2) -> 33.39
A105: P2 Potencia | B105: 6.928 | C105: 30 | D105: 1.31928 | E105: 2.37 | F105: =ROUND(B105*E105,2) -> 16.42 | H105: 6.928 | I105: 2.37 | J105: =ROUND(H105*I105,2) -> 16.42 | L105: 6.928 | M105: 2.37 | N105: =ROUND(L105*M105,2) -> 16.42 | P105: Importe mensual cobrado (€) · 24 meses ▾
A106: P1 Energía | B106: 182.17 | C106: 30 | D106: 0.111171 | E106: 0.17 | F106: =ROUND(B106*E106,2) -> 30.97 | H106: 381.405 | I106: 0.1724 | J106: =ROUND(H106*I106,2) -> 65.75 | L106: 82.17 | M106: 0.175 | N106: =ROUND(L106*M106,2) -> 14.38
A107: P2 Energía | B107: 176.133 | C107: 30 | D107: 0.111171 | E107: 0.17 | F107: =ROUND(B107*E107,2) -> 29.94 | H107: 356.448 | I107: 0.1724 | J107: =ROUND(H107*I107,2) -> 61.45 | L107: 76.133 | M107: 0.175 | N107: =ROUND(L107*M107,2) -> 13.32
A108: P3 Energía | B108: 270.26 | C108: 30 | D108: 0.111171 | E108: 0.17 | F108: =ROUND(B108*E108,2) -> 45.94 | H108: 667.21 | I108: 0.1724 | J108: =ROUND(H108*I108,2) -> 115.03 | L108: 170.26 | M108: 0.175 | N108: =ROUND(L108*M108,2) -> 29.8
...

Sheet _series
A1: nf | B1: 2024-07 | C1: 2024-08 | D1: 2024-09 | E1: 2024-10 | F1: 2024-11 | G1: 2024-12 | H1: 2025-01 | I1: 2025-02 | J1: 2025-03 | K1: 2025-04 | L1: 2025-05 | M1: 2025-06 | N1: 2025-07 | O1: 2025-08 | P1: 2025-09 | Q1: 2025-10 | R1: 2025-11 | S1: 2025-12 | T1: 2026-01 | U1: 2026-02 | V1: 2026-03 | W1: 2026-04 | X1: 2026-05 | Y1: 2026-06
A2: 8550 | B2: 0 | C2: 0 | D2: 0 | E2: 0 | F2: 0 | G2: 67.85 | H2: 291.23 | I2: 212.91 | J2: 183.41 | K2: 146.93 | L2: 240.12 | M2: 360.36 | N2: 489.63 | O2: 103.62 | P2: 664.91 | Q2: 334.22 | R2: 254.97 | S2: 121.53 | T2: 392.65 | U2: 287.51 | V2: 349.44 | W2: 199.21 | X2: 273.87 | Y2: 430.03
A3: 8551 | B3: 0 | C3: 0 | D3: 0 | E3: 0 | F3: 0 | G3: 122.79 | H3: 257.6 | I3: 149.89 | J3: 179.34 | K3: 133.56 | L3: 217.18 | M3: 255.1 | N3: 355.24 | O3: 132.59 | P3: 333.79 | Q3: 306.02 | R3: 209.78 | S3: 189.38 | T3: 339.72 | U3: 188.55 | V3: 237.18 | W3: 186.2 | X3: 276 | Y3: 343.77
A4: 8552 | B4: 0 | C4: 0 | D4: 0 | E4: 0 | F4: 0 | G4: 240.78 | H4: 270.33 | I4: 122.02 | J4: 156.75 | K4: 185.58 | L4: 220.94 | M4: 589.63 | N4: 626.48 | O4: 164.89 | P4: 386.56 | Q4: 382.69 | R4: 261.9 | S4: 330.96 | T4: 371.28 | U4: 169.53 | V4: 214.78 | W4: 271.98 | X4: 271.88 | Y4: 692.94
A5: 8553 | B5: 0 | C5: 0 | D5: 0 | E5: 0 | F5: 0 | G5: 143.34 | H5: 255.18 | I5: 122.89 | J5: 228.55 | K5: 175.12 | L5: 270.51 | M5: 388.07 | N5: 574.82 | O5: 154.53 | P5: 359.42 | Q5: 352.4 | R5: 177.06 | S5: 261.13 | T5: 337.12 | U5: 149.42 | V5: 232.63 | W5: 279.54 | X5: 333.42 | Y5: 462.7
A6: 8554 | B6: 0 | C6: 0 | D6: 0 | E6: 0 | F6: 0 | G6: 181.06 | H6: 235.48 | I6: 115.38 | J6: 164.69 | K6: 208.48 | L6: 620.36 | M6: 776.69 | N6: 910.68 | O6: 276.4 | P6: 777.08 | Q6: 555.31 | R6: 267.98 | S6: 240.42 | T6: 316.78 | U6: 165.48 | V6: 218.11 | W6: 311.55 | X6: 651.31 | Y6: 839.16
A7: 8555 | B7: 0 | C7: 0 | D7: 0 | E7: 0 | F7: 0 | G7: 98.79 | H7: 169.59 | I7: 113.34 | J7: 142.42 | K7: 111.81 | L7: 150.31 | M7: 280.5 | N7: 374.5 | O7: 130.26 | P7: 333.66 | Q7: 240.63 | R7: 117.47 | S7: 166.39 | T7: 229.98 | U7: 152.99 | V7: 196.1 | W7: 164.11 | X7: 189.25 | Y7: 351.03
A8: 8556 | B8: 0 | C8: 0 | D8: 0 | E8: 0 | F8: 0 | G8: 170.28 | H8: 258.52 | I8: 181.42 | J8: 255.74 | K8: 242.83 | L8: 303.68 | M8: 367.91 | N8: 611.02 | O8: 163.33 | P8: 392.33 | Q8: 376.51 | R8: 126.21 | S8: 230.73 | T8: 340.4 | U8: 259.71 | V8: 311.91 | W8: 314.39 | X8: 371.77 | Y8: 505.17
A9: 8557 | B9: 0 | C9: 0 | D9: 0 | E9: 0 | F9: 0 | G9: 193.05 | H9: 309.11 | I9: 197.99 | J9: 256.8 | K9: 114.01 | L9: 245.88 | M9: 405.6 | N9: 510.83 | O9: 181.08 | P9: 334.97 | Q9: 263.34 | R9: 146.93 | S9: 251.21 | T9: 411.51 | U9: 292.86 | V9: 309.03 | W9: 166.4 | X9: 321.26 | Y9: 473.59
A10: 8558 | B10: 0 | C10: 0 | D10: 0 | E10: 0 | F10: 0 | G10: 131.4 | H10: 332.79 | I10: 154.85 | J10: 172.58 | K10: 151.87 | L10: 305.89 | M10: 454 | N10: 499.25 | O10: 117.75 | P10: 483.02 | Q10: 456.69 | R10: 281.62 | S10: 195.74 | T10: 435.76 | U10: 244.72 | V10: 225.93 | W10: 215.79 | X10: 358.91 | Y10: 525.02
A11: 8559 | B11: 0 | C11: 0 | D11: 0 | E11: 0 | F11: 0 | G11: 85.02 | H11: 92.48 | I11: 67.3 | J11: 63.22 | K11: 67.94 | L11: 131.71 | M11: 173.41 | N11: 247.92 | O11: 108.06 | P11: 101.19 | Q11: 77.36 | R11: 93.5 | S11: 135.59 | T11: 150.61 | U11: 101.26 | V11: 83.58 | W11: 92.95 | X11: 164.49 | Y11: 244.04
A12: 8560 | B12: 0 | C12: 0 | D12: 0 | E12: 0 | F12: 0 | G12: 51.19 | H12: 153.54 | I12: 125.01 | J12: 130.52 | K12: 91.61 | L12: 150.09 | M12: 209.74 | N12: 185.37 | O12: 131.51 | P12: 105.59 | Q12: 72.64 | R12: 89.99 | S12: 123.52 | T12: 213.59 | U12: 175.89 | V12: 185.75 | W12: 115.98 | X12: 187.53 | Y12: 400.32
A13: 8561 | B13: 0 | C13: 0 | D13: 0 | E13: 0 | F13: 0 | G13: 114.46 | H13: 156.2 | I13: 110.71 | J13: 260.77 | K13: 179.33 | L13: 224.35 | M13: 412.73 | N13: 606.87 | O13: 152.73 | P13: 491.2 | Q13: 404.96 | R13: 240.01 | S13: 180.49 | T13: 212.19 | U13: 175.43 | V13: 339.01 | W13: 251.07 | X13: 287 | Y13: 499.04
... A137: 8730 | B137: 0 | C137: 0 | D137: 0 | E137: 0 | F137: 480.78 | G137: 869.3 | H137: 484.66 | I137: 499.94 | J137: 802.97 | K137: 1074.48 | L137: 997.35 | M137: 1001.22 | N137: 1957.85 | O137: 79.62 | P137: 1019.69 | Q137: 699.4 | R137: 233.98 | S137: 803.7 | T137: 716.71 | U137: 712.12 | V137: 540.74 | W137: 624.71 | X137: 0 | Y137: 0
