Workbook

Sheet Resumen
A1: RESUMEN · 27 facturas 3.0TD · abril 2026 · margen abril vivo (editable) + histórico del CUPS (HOJA TTVA LUZ)
A2: LEYENDA | B2: APROBAR ≥30% | D2: REVISAR 20–30% | F2: RECHAZAR <20% · margen objetivo editable en Detalle
A4: Factura | B4: Cliente | C4: Nombre | D4: Prov. | E4: Margen abril | F4: Veredicto | G4: Margen hist. | H4: Cobrado hist. | I4: Qué revisar
A5: 8544 | B5: C02330 | C5: ORENCO 2019, S.L. | D5: Naturgy | E5: =Detalle!B17 -> 0.17898769 | F5: =IF(Detalle!B17>=0.3,"APROBAR",IF(Detalle!B17>=0.2,"REVISAR","RECHAZAR")) -> RECHAZAR | G5: 0.275 | H5: 40716.44 | I5: =IF(Detalle!B17>=0.3,"OK · registrar",IF(Detalle!B17>=0.2,"Margen abril <30%","Margen abril <20% · subir objetivo o renegociar"))&"" -> Margen abril <20% · subir objetivo o renegociar
A6: 8545 | B6: C01200 | C6: SOLUCIONES GASTRONÓMICAS DE JAVEA 2014, S.L. | D6: Naturgy | E6: =Detalle!B35 -> 0.20960183 | F6: =IF(Detalle!B35>=0.3,"APROBAR",IF(Detalle!B35>=0.2,"REVISAR","RECHAZAR")) -> REVISAR | G6: 0.244 | H6: 53718.09 | I6: =IF(Detalle!B35>=0.3,"OK · registrar",IF(Detalle!B35>=0.2,"Margen abril <30%","Margen abril <20% · subir objetivo o renegociar"))&"" -> Margen abril <30%
A7: 8546 | B7: C03270 | C7: LULU BEACH CLUB JAVEA SL | D7: Naturgy | E7: =Detalle!B53 -> 0.033690116 | F7: =IF(Detalle!B53>=0.3,"APROBAR",IF(Detalle!B53>=0.2,"REVISAR","RECHAZAR")) -> RECHAZAR | G7: 0.204 | H7: 12272.46 | I7: =IF(Detalle!B53>=0.3,"OK · registrar",IF(Detalle!B53>=0.2,"Margen abril <30%","Margen abril <20% · subir objetivo o renegociar"))&"" -> Margen abril <20% · subir objetivo o renegociar
A8: 8547 | B8: C01770 | C8: CASA LILI JAVEA, S.L. | D8: ? | E8: =Detalle!B72 -> 0.30715088 | F8: =IF(Detalle!B72>=0.3,"APROBAR",IF(Detalle!B72>=0.2,"REVISAR","RECHAZAR")) -> APROBAR | G8: 0.432 | H8: 130568.72 | I8: =IF(Detalle!B72>=0.3,"OK · registrar",IF(Detalle!B72>=0.2,"Margen abril <30%","Margen abril <20% · subir objetivo o renegociar"))&" · Es 6.1TD (no 3.0TD)" -> OK · registrar · Es 6.1TD (no 3.0TD)
A9: 8564 | B9: C01930 | C9: FUNDACIÓN FSU PROGRAMAS INTERNACIONALES | D9: Naturgy | E9: =Detalle!B90 -> 0.35858241 | F9: =IF(Detalle!B90>=0.3,"APROBAR",IF(Detalle!B90>=0.2,"REVISAR","RECHAZAR")) -> APROBAR | G9: 0.269 | H9: 18857.1 | I9: =IF(Detalle!B90>=0.3,"OK · registrar",IF(Detalle!B90>=0.2,"Margen abril <30%","Margen abril <20% · subir objetivo o renegociar"))&"" -> OK · registrar
A10: 8565 | B10: C01920 | C10: FUNDACIÓN FSU PROGRAMAS INTERNACIONALES | D10: Naturgy | E10: =Detalle!B108 -> 0.33436081 | F10: =IF(Detalle!B108>=0.3,"APROBAR",IF(Detalle!B108>=0.2,"REVISAR","RECHAZAR")) -> APROBAR | G10: 0.324 | H10: 19336.5 | I10: =IF(Detalle!B108>=0.3,"OK · registrar",IF(Detalle!B108>=0.2,"Margen abril <30%","Margen abril <20% · subir objetivo o renegociar"))&"" -> OK · registrar
A11: 8566 | B11: C01910 | C11: FUNDACIÓN FSU PROGRAMAS INTERNACIONALES | D11: Naturgy | E11: =Detalle!B126 -> 0.32661503 | F11: =IF(Detalle!B126>=0.3,"APROBAR",IF(Detalle!B126>=0.2,"REVISAR","RECHAZAR")) -> APROBAR | G11: 0.342 | H11: 10564.26 | I11: =IF(Detalle!B126>=0.3,"OK · registrar",IF(Detalle!B126>=0.2,"Margen abril <30%","Margen abril <20% · subir objetivo o renegociar"))&"" -> OK · registrar
A12: 8567 | B12: C00790 | C12: CASA LILI, S.L. | D12: Naturgy | E12: =Detalle!B145 -> 0.16289997 | F12: =IF(Detalle!B145>=0.3,"APROBAR",IF(Detalle!B145>=0.2,"REVISAR","RECHAZAR")) -> RECHAZAR | G12: 0.405 | H12: 151868.44 | I12: =IF(Detalle!B145>=0.3,"OK · registrar",IF(Detalle!B145>=0.2,"Margen abril <30%","Margen abril <20% · subir objetivo o renegociar"))&"" -> Margen abril <20% · subir objetivo o renegociar
A13: 8578 | B13: C02180 | C13: EDWIN BAUMGARTNER | D13: Naturgy | E13: =Detalle!B163 -> 0.30823789 | F13: =IF(Detalle!B163>=0.3,"APROBAR",IF(Detalle!B163>=0.2,"REVISAR","RECHAZAR")) -> APROBAR | G13: 0.487 | H13: 2907.71 | I13: =IF(Detalle!B163>=0.3,"OK · registrar",IF(Detalle!B163>=0.2,"Margen abril <30%","Margen abril <20% · subir objetivo o renegociar"))&"" -> OK · registrar
A14: 8615 | B14: C01220 | C14: VIVES ELECTRODOMÉSTICOS, S.L. | D14: Repsol | E14: =Detalle!B181 -> 0.13307223 | F14: =IF(Detalle!B181>=0.3,"APROBAR",IF(Detalle!B181>=0.2,"REVISAR","RECHAZAR")) -> RECHAZAR | G14: 0.316 | H14: 26924.82 | I14: =IF(Detalle!B181>=0.3,"OK · registrar",IF(Detalle!B181>=0.2,"Margen abril <30%","Margen abril <20% · subir objetivo o renegociar"))&" · Repsol margen muy bajo" -> Margen abril <20% · subir objetivo o renegociar · Repsol margen muy bajo
A15: 8629 | B15: C01510 | C15: CAFE ZUR BACKSTUBE, S.L. | D15: Naturgy | E15: =Detalle!B199 -> 0.29787383 | F15: =IF(Detalle!B199>=0.3,"APROBAR",IF(Detalle!B199>=0.2,"REVISAR","RECHAZAR")) -> REVISAR | G15: 0.362 | H15: 6192.61 | I15: =IF(Detalle!B199>=0.3,"OK · registrar",IF(Detalle!B199>=0.2,"Margen abril <30%","Margen abril <20% · subir objetivo o renegociar"))&"" -> Margen abril <30%
A16: 8635 | B16: C01630 | C16: ALEJANDRO BOX CANDELA | D16: Naturgy | E16: =Detalle!B217 -> 0.16804865 | F16: =IF(Detalle!B217>=0.3,"APROBAR",IF(Detalle!B217>=0.2,"REVISAR","RECHAZAR")) -> RECHAZAR | G16: 0.277 | H16: 31335.42 | I16: =IF(Detalle!B217>=0.3,"OK · registrar",IF(Detalle!B217>=0.2,"Margen abril <30%","Margen abril <20% · subir objetivo o renegociar"))&"" -> Margen abril <20% · subir objetivo o renegociar
A17: 8638 | B17: C01710 | C17: FARMACIA ESPINÓS | D17: Repsol | E17: =Detalle!B235 -> 0.16678386 | F17: =IF(Detalle!B235>=0.3,"APROBAR",IF(Detalle!B235>=0.2,"REVISAR","RECHAZAR")) -> RECHAZAR | G17: 0.253 | H17: 14704.48 | I17: =IF(Detalle!B235>=0.3,"OK · registrar",IF(Detalle!B235>=0.2,"Margen abril <30%","Margen abril <20% · subir objetivo o renegociar"))&"" -> Margen abril <20% · subir objetivo o renegociar
A18: 8644 | B18: C01840 | C18: JOSE GUILLERMO CHOLBI SART | D18: Naturgy | E18: =Detalle!B253 -> 0.33509687 | F18: =IF(Detalle!B253>=0.3,"APROBAR",IF(Detalle!B253>=0.2,"REVISAR","RECHAZAR")) -> APROBAR | G18: 0.184 | H18: 3367.63 | I18: =IF(Detalle!B253>=0.3,"OK · registrar",IF(Detalle!B253>=0.2,"Margen abril <30%","Margen abril <20% · subir objetivo o renegociar"))&"" -> OK · registrar
A19: 8649 | B19: C01980 | C19: TINTORERÍA LAVANDERÍA COLOMER | D19: Repsol | E19: =Detalle!B271 -> 0.21949185 | F19: =IF(Detalle!B271>=0.3,"APROBAR",IF(Detalle!B271>=0.2,"REVISAR","RECHAZAR")) -> REVISAR | G19: 0.203 | H19: 15417.71 | I19: =IF(Detalle!B271>=0.3,"OK · registrar",IF(Detalle!B271>=0.2,"Margen abril <30%","Margen abril <20% · subir objetivo o renegociar"))&" · P6 a precio doble (real)" -> Margen abril <30% · P6 a precio doble (real)
A20: 8652 | B20: C02180 | C20: EDWIN BAUMGARTNER | D20: Naturgy | E20: =Detalle!B289 -> 0.30823789 | F20: =IF(Detalle!B289>=0.3,"APROBAR",IF(Detalle!B289>=0.2,"REVISAR","RECHAZAR")) -> APROBAR | G20: 0.487 | H20: 2907.71 | I20: =IF(Detalle!B289>=0.3,"OK · registrar",IF(Detalle!B289>=0.2,"Margen abril <30%","Margen abril <20% · subir objetivo o renegociar"))&"" -> OK · registrar
A21: 8669 | B21: C02600 | C21: CRISTIAN FERRARI | D21: Naturgy | E21: =Detalle!B307 -> 0.2360357 | F21: =IF(Detalle!B307>=0.3,"APROBAR",IF(Detalle!B307>=0.2,"REVISAR","RECHAZAR")) -> REVISAR | G21: 0.292 | H21: 5897.71 | I21: =IF(Detalle!B307>=0.3,"OK · registrar",IF(Detalle!B307>=0.2,"Margen abril <30%","Margen abril <20% · subir objetivo o renegociar"))&"" -> Margen abril <30%
A22: 8684 | B22: C02910 | C22: NICHOLAS JAMES RATCLIFFE | D22: Repsol | E22: =Detalle!B325 -> 0.25181786 | F22: =IF(Detalle!B325>=0.3,"APROBAR",IF(Detalle!B325>=0.2,"REVISAR","RECHAZAR")) -> REVISAR | G22: 0.424 | H22: 4741.93 | I22: =IF(Detalle!B325>=0.3,"OK · registrar",IF(Detalle!B325>=0.2,"Margen abril <30%","Margen abril <20% · subir objetivo o renegociar"))&"" -> Margen abril <30%
A23: 8691 | B23: C03020 | C23: MONTGO SEGURIDAD S.L. | D23: Repsol | E23: =Detalle!B343 -> 0.07172886 | F23: =IF(Detalle!B343>=0.3,"APROBAR",IF(Detalle!B343>=0.2,"REVISAR","RECHAZAR")) -> RECHAZAR | G23: 0.154 | H23: 2756.73 | I23: =IF(Detalle!B343>=0.3,"OK · registrar",IF(Detalle!B343>=0.2,"Margen abril <30%","Margen abril <20% · subir objetivo o renegociar"))&"" -> Margen abril <20% · subir objetivo o renegociar
A24: 8705 | B24: C03200 | C24: 2 HANDS FULL, S.L | D24: Repsol | E24: =Detalle!B361 -> 0.069009331 | F24: =IF(Detalle!B361>=0.3,"APROBAR",IF(Detalle!B361>=0.2,"REVISAR","RECHAZAR")) -> RECHAZAR | G24: 0.147 | H24: 3844.21 | I24: =IF(Detalle!B361>=0.3,"OK · registrar",IF(Detalle!B361>=0.2,"Margen abril <30%","Margen abril <20% · subir objetivo o renegociar"))&"" -> Margen abril <20% · subir objetivo o renegociar
A25: 8731 | B25: C01500 | C25: SANTIAGO JAVIER NUÑEZ JOVER | D25: Repsol | E25: =Detalle!B379 -> 0.163502 | F25: =IF(Detalle!B379>=0.3,"APROBAR",IF(Detalle!B379>=0.2,"REVISAR","RECHAZAR")) -> RECHAZAR | G25: 0.306 | H25: 43740 | I25: =IF(Detalle!B379>=0.3,"OK · registrar",IF(Detalle!B379>=0.2,"Margen abril <30%","Margen abril <20% · subir objetivo o renegociar"))&" · P6 doble (real); abril sin consumo" -> Margen abril <20% · subir objetivo o renegociar · P6 doble (real); abril sin consumo
A26: 8732 | B26: C02430 | C26: CINDY DEPERE | D26: Naturgy | E26: =Detalle!B398 -> 0.26203771 | F26: =IF(Detalle!B398>=0.3,"APROBAR",IF(Detalle!B398>=0.2,"REVISAR","RECHAZAR")) -> REVISAR | G26: 0.31 | H26: 14442.13 | I26: =IF(Detalle!B398>=0.3,"OK · registrar",IF(Detalle!B398>=0.2,"Margen abril <30%","Margen abril <20% · subir objetivo o renegociar"))&" · Excedentes solares NO compensados" -> Margen abril <30% · Excedentes solares NO compensados
A27: 8733 | B27: C03410 | C27: NORAY PUERTO 2012 S.L. | D27: Naturgy | E27: =Detalle!B416 -> 0.18029709 | F27: =IF(Detalle!B416>=0.3,"APROBAR",IF(Detalle!B416>=0.2,"REVISAR","RECHAZAR")) -> RECHAZAR | G27: 0.326 | H27: 5854.69 | I27: =IF(Detalle!B416>=0.3,"OK · registrar",IF(Detalle!B416>=0.2,"Margen abril <30%","Margen abril <20% · subir objetivo o renegociar"))&"" -> Margen abril <20% · subir objetivo o renegociar
A28: 8734 | B28: C01820 | C28: PIZZERIA TIGER, S.L. | D28: Naturgy | E28: =Detalle!B434 -> 0.21443777 | F28: =IF(Detalle!B434>=0.3,"APROBAR",IF(Detalle!B434>=0.2,"REVISAR","RECHAZAR")) -> REVISAR | G28: 0.347 | H28: 33692.13 | I28: =IF(Detalle!B434>=0.3,"OK · registrar",IF(Detalle!B434>=0.2,"Margen abril <30%","Margen abril <20% · subir objetivo o renegociar"))&"" -> Margen abril <30%
A29: 8735 | B29: C02700 | C29: TALLERES MARTINEZ JAVEA SL | D29: Repsol | E29: =Detalle!B452 -> 0.047489346 | F29: =IF(Detalle!B452>=0.3,"APROBAR",IF(Detalle!B452>=0.2,"REVISAR","RECHAZAR")) -> RECHAZAR | G29: 0.129 | H29: 14832.89 | I29: =IF(Detalle!B452>=0.3,"OK · registrar",IF(Detalle!B452>=0.2,"Margen abril <30%","Margen abril <20% · subir objetivo o renegociar"))&"" -> Margen abril <20% · subir objetivo o renegociar
A30: 8737 | B30: C00740 | C30: PIZZERIA ORBA, S.L. | D30: Naturgy | E30: =Detalle!B470 -> 0.20018502 | F30: =IF(Detalle!B470>=0.3,"APROBAR",IF(Detalle!B470>=0.2,"REVISAR","RECHAZAR")) -> REVISAR | G30: 0.314 | H30: 82412.04 | I30: =IF(Detalle!B470>=0.3,"OK · registrar",IF(Detalle!B470>=0.2,"Margen abril <30%","Margen abril <20% · subir objetivo o renegociar"))&"" -> Margen abril <30%
A31: 8738 | B31: C02620 | C31: JAVEA PADEL & Tenis SL | D31: Naturgy | E31: =Detalle!B488 -> 0.16668595 | F31: =IF(Detalle!B488>=0.3,"APROBAR",IF(Detalle!B488>=0.2,"REVISAR","RECHAZAR")) -> RECHAZAR | G31: 0.324 | H31: 40860.13 | I31: =IF(Detalle!B488>=0.3,"OK · registrar",IF(Detalle!B488>=0.2,"Margen abril <30%","Margen abril <20% · subir objetivo o renegociar"))&"" -> Margen abril <20% · subir objetivo o renegociar
A33: Margen abril editable en TODAS (celda amarilla en Detalle). Margen hist., cobrado y mejor/peor mes vienen de HOJA TTVA LUZ por CUPS.

Sheet Detalle
A1: Factura 8544 · C02330 · ORENCO 2019, S.L. | I1: ES0021000001197056KH · Naturgy · 01/04/26 a 30/04/26 · PC real leído: 01MAR_31MAR26 (P2/P3/P6) + plan fijo | R1: HISTÓRICO DEL CUPS · HOJA TTVA LUZ
A2: Concepto | B2: PENDIENTE (sin registrar) | H2: MES ANTERIOR · Fact.6296 (01/03/26 a 31/03/26) | L2: AÑO ANTERIOR · Fact.4508 (01/04/25 a 30/04/25) | R2: Cobrado total: 40.716 €
B3: Cant | C3: Días | D3: PC real | E3: PV | F3: Importe | H3: Cant | I3: PV | J3: Importe | L3: Cant | M3: PV | N3: Importe | R3: Pagado total: 29.523 €
A4: P1 Potencia | B4: 30 | C4: 30 | D4: 1.73784 | E4: 2.5542 | F4: =ROUND(B4*E4,2) -> 76.63 | H4: 30 | I4: 2.5542 | J4: =ROUND(H4*I4,2) -> 76.63 | L4: 30 | M4: 2.5542 | N4: =ROUND(L4*M4,2) -> 76.63 | R4: DIF: 11.193 € · Margen hist.: 27.5%
A5: P2 Potencia | B5: 30 | C5: 30 | D5: 0.9357 | E5: 1.37733 | F5: =ROUND(B5*E5,2) -> 41.32 | H5: 30 | I5: 1.37733 | J5: =ROUND(H5*I5,2) -> 41.32 | L5: 30 | M5: 1.37733 | N5: =ROUND(L5*M5,2) -> 41.32 | R5: Mejor mes: 2024-06 · 3.014 € · margen 56%
A6: P3 Potencia | B6: 30 | C6: 30 | D6: 0.43137 | E6: 0.62868 | F6: =ROUND(B6*E6,2) -> 18.86 | H6: 30 | I6: 0.62868 | J6: =ROUND(H6*I6,2) -> 18.86 | L6: 30 | M6: 0.62868 | N6: =ROUND(L6*M6,2) -> 18.86 | R6: Peor mes: 2024-11 · 701 € · margen 39%
A7: P4 Potencia | B7: 30 | C7: 30 | D7: 0.38244 | E7: 0.5561 | F7: =ROUND(B7*E7,2) -> 16.68 | H7: 30 | I7: 0.5561 | J7: =ROUND(H7*I7,2) -> 16.68 | L7: 30 | M7: 0.5561 | N7: =ROUND(L7*M7,2) -> 16.68 | R7: ⚠ Consumo en P1/P2 (calendario inactivo) → consolidado a P4/P5/P6
A8: P5 Potencia | B8: 30 | C8: 30 | D8: 0.26964 | E8: 0.3868 | F8: =ROUND(B8*E8,2) -> 11.6 | H8: 30 | I8: 0.3868 | J8: =ROUND(H8*I8,2) -> 11.6 | L8: 30 | M8: 0.3868 | N8: =ROUND(L8*M8,2) -> 11.6 | R8: Importe mensual cobrado (€) · últimos 24 meses
A9: P6 Potencia | B9: 30 | C9: 30 | D9: 0.18156 | E9: 0.2653 | F9: =ROUND(B9*E9,2) -> 7.96 | H9: 30 | I9: 0.2653 | J9: =ROUND(H9*I9,2) -> 7.96 | L9: 30 | M9: 0.2653 | N9: =ROUND(L9*M9,2) -> 7.96
A10: P4 Energía | B10: =IF($P$10="",2517.101,ROUND(2517.101*((1087.3487/(1-$P$10))-173.05)/1151.35,2)) -> 2517.101 | D10: 0.121236 | E10: 0.139 | F10: =ROUND(B10*E10,2) -> 349.88 | H10: 2317.101 | I10: 0.139 | J10: =ROUND(H10*I10,2) -> 322.08 | L10: 1937.42 | M10: 0.145 | N10: =ROUND(L10*M10,2) -> 280.93 | O10: Margen objetivo (edita el % aquí) ▶
A11: P5 Energía | B11: =IF($P$10="",2364.265,ROUND(2364.265*((1087.3487/(1-$P$10))-173.05)/1151.35,2)) -> 2364.265 | D11: 0.114444 | E11: 0.138 | F11: =ROUND(B11*E11,2) -> 326.27 | H11: 2064.265 | I11: 0.138 | J11: =ROUND(H11*I11,2) -> 284.87 | L11: 1611.579 | M11: 0.139 | N11: =ROUND(L11*M11,2) -> 224.01 | O11: Cant. P4/P5/P6 suben en proporción
A12: P6 Energía | B12: =IF($P$10="",3683.741,ROUND(3683.741*((1087.3487/(1-$P$10))-173.05)/1151.35,2)) -> 3683.741 | D12: 0.106808 | E12: 0.129 | F12: =ROUND(B12*E12,2) -> 475.2 | H12: 3383.741 | I12: 0.129 | J12: =ROUND(H12*I12,2) -> 436.5 | L12: 2928.76 | M12: 0.139 | N12: =ROUND(L12*M12,2) -> 407.1 | O12: para cumplir ese margen
A13: Alquiler contador | B13: 1 | D13: 17.615 | E13: 17.615 | F13: =ROUND(B13*E13,2) -> 17.62 | H13: 1 | I13: 17.615 | J13: =ROUND(H13*I13,2) -> 17.62 | L13: 1 | M13: 17.615 | N13: =ROUND(L13*M13,2) -> 17.62
A14: Bono social | B14: 30 | D14: 0.01912 | E14: 0.01912 | F14: =ROUND(B14*E14,2) -> 0.57 | H14: 30 | I14: 0.01274 | J14: =ROUND(H14*I14,2) -> 0.38 | L14: 30 | M14: 0.01274 | N14: =ROUND(L14*M14,2) -> 0.38
A15: Tasa eléctrica | B15: 71.99 | D15: 1 | E15: 1 | F15: =ROUND(B15*E15,2) -> 71.99 | H15: 66.49 | I15: 1 | J15: =ROUND(H15*I15,2) -> 66.49 | L15: 62.66 | M15: 1 | N15: =ROUND(L15*M15,2) -> 62.66
A16: TOTAL c/IVA | F16: =ROUND((SUM(F4:F15)-F15)*1.21+F15,2) -> 1696.52 | J16: =ROUND((SUM(J4:J15)-J15)*1.21+J15,2) -> 1560.24 | N16: =ROUND((SUM(N4:N15)-N15)*1.21+N15,2) -> 1397.4
A17: MARGEN sin registrar | B17: =(SUM(F4:F12)-1087.3487)/SUM(F4:F12) -> 0.17898769 | L17: =IF(B17>=0.3,"APROBAR",IF(B17>=0.2,"REVISAR","RECHAZAR")) -> RECHAZAR
A19: Factura 8545 · C01200 · SOLUCIONES GASTRONÓMICAS DE JAVEA 2014, S.L. | I19: ES0021000001209594ZK · Naturgy · 01/04/26 a 30/04/26 · PC maestro (=factura real, verificado) | R19: HISTÓRICO DEL CUPS · HOJA TTVA LUZ
A20: Concepto | B20: PENDIENTE (sin registrar) | H20: MES ANTERIOR · Fact.6297 (01/03/26 a 31/03/26) | L20: AÑO ANTERIOR · Fact.4514 (01/04/25 a 30/04/25) | R20: Cobrado total: 53.718 €
B21: Cant | C21: Días | D21: PC real | E21: PV | F21: Importe | H21: Cant | I21: PV | J21: Importe | L21: Cant | M21: PV | N21: Importe | R21: Pagado total: 40.613 €
A22: P1 Potencia | B22: 17.32 | C22: 30 | D22: 1.73784 | E22: 1.999 | F22: =ROUND(B22*E22,2) -> 34.62 | H22: 17.32 | I22: 1.999 | J22: =ROUND(H22*I22,2) -> 34.62 | L22: 17.32 | M22: 2.5542 | N22: =ROUND(L22*M22,2) -> 44.24 | R22: DIF: 13.105 € · Margen hist.: 24.4%
A23: P2 Potencia | B23: 17.32 | C23: 30 | D23: 0.9357 | E23: 1.811 | F23: =ROUND(B23*E23,2) -> 31.37 | H23: 17.32 | I23: 1.811 | J23: =ROUND(H23*I23,2) -> 31.37 | L23: 17.32 | M23: 1.3773 | N23: =ROUND(L23*M23,2) -> 23.85 | R23: Mejor mes: 2024-08 · 2.606 € · margen 23%
A24: P3 Potencia | B24: 17.32 | C24: 30 | D24: 0.43137 | E24: 0.6161 | F24: =ROUND(B24*E24,2) -> 10.67 | H24: 17.32 | I24: 0.6161 | J24: =ROUND(H24*I24,2) -> 10.67 | L24: 17.32 | M24: 0.6286 | N24: =ROUND(L24*M24,2) -> 10.89 | R24: Peor mes: 2023-01 · 446 € · margen 25%
A25: P4 Potencia | B25: 17.32 | C25: 30 | D25: 0.38244 | E25: 0.5551 | F25: =ROUND(B25*E25,2) -> 9.61 | H25: 17.32 | I25: 0.5551 | J25: =ROUND(H25*I25,2) -> 9.61 | L25: 17.32 | M25: 0.5561 | N25: =ROUND(L25*M25,2) -> 9.63 | R25: ⚠ Consumo en P1/P2 (calendario inactivo) → consolidado a P4/P5/P6
A26: P5 Potencia | B26: 17.32 | C26: 30 | D26: 0.26964 | E26: 0.595 | F26: =ROUND(B26*E26,2) -> 10.31 | H26: 17.32 | I26: 0.595 | J26: =ROUND(H26*I26,2) -> 10.31 | L26: 17.32 | M26: 0.3868 | N26: =ROUND(L26*M26,2) -> 6.7 | R26: Importe mensual cobrado (€) · últimos 24 meses
A27: P6 Potencia | B27: 17.32 | C27: 30 | D27: 0.18156 | E27: 0.4523 | F27: =ROUND(B27*E27,2) -> 7.83 | H27: 17.32 | I27: 0.4523 | J27: =ROUND(H27*I27,2) -> 7.83 | L27: 17.32 | M27: 0.2653 | N27: =ROUND(L27*M27,2) -> 4.59
A28: P4 Energía | B28: =IF($P$28="",1691.432,ROUND(1691.432*((803.9614/(1-$P$28))-104.41)/912.75,2)) -> 1691.432 | D28: 0.121236 | E28: 0.149 | F28: =ROUND(B28*E28,2) -> 252.02 | H28: 1474.716 | I28: 0.15 | J28: =ROUND(H28*I28,2) -> 221.21 | L28: 1570.18 | M28: 0.16 | N28: =ROUND(L28*M28,2) -> 251.23 | O28: Margen objetivo (edita el % aquí) ▶
A29: P5 Energía | B29: =IF($P$28="",2156.035,ROUND(2156.035*((803.9614/(1-$P$28))-104.41)/912.75,2)) -> 2156.035 | D29: 0.114444 | E29: 0.14 | F29: =ROUND(B29*E29,2) -> 301.84 | H29: 1814.66 | I29: 0.149 | J29: =ROUND(H29*I29,2) -> 270.38 | L29: 1034.274 | M29: 0.155 | N29: =ROUND(L29*M29,2) -> 160.31 | O29: Cant. P4/P5/P6 suben en proporción
A30: P6 Energía | B30: =IF($P$28="",2658.43,ROUND(2658.43*((803.9614/(1-$P$28))-104.41)/912.75,2)) -> 2658.43 | D30: 0.106808 | E30: 0.135 | F30: =ROUND(B30*E30,2) -> 358.89 | H30: 2225.184 | I30: 0.139 | J30: =ROUND(H30*I30,2) -> 309.3 | L30: 2165.73 | M30: 0.135 | N30: =ROUND(L30*M30,2) -> 292.37 | O30: para cumplir ese margen
A31: Alquiler contador | B31: 1 | D31: 17.615 | E31: 17.615 | F31: =ROUND(B31*E31,2) -> 17.62 | H31: 1 | I31: 17.615 | J31: =ROUND(H31*I31,2) -> 17.62 | L31: 1 | M31: 17.615 | N31: =ROUND(L31*M31,2) -> 17.62
A32: Bono social | B32: 5 | D32: 0.01912 | E32: 0.01912 | F32: =ROUND(B32*E32,2) -> 0.1 | H32: 5 | I32: 0.01912 | J32: =ROUND(H32*I32,2) -> 0.1 | L32: 30 | M32: 0.01274 | N32: =ROUND(L32*M32,2) -> 0.38
A33: Tasa eléctrica | B33: 59.26 | D33: 1 | E33: 1 | F33: =ROUND(B33*E33,2) -> 59.26 | H33: 49.46 | I33: 1 | J33: =ROUND(H33*I33,2) -> 49.46 | L33: 44 | M33: 1 | N33: =ROUND(L33*M33,2) -> 44
A34: TOTAL c/IVA | F34: =ROUND((SUM(F22:F33)-F33)*1.21+F33,2) -> 1311.46 | J34: =ROUND((SUM(J22:J33)-J33)*1.21+J33,2) -> 1166.31 | N34: =ROUND((SUM(N22:N33)-N33)*1.21+N33,2) -> 1038.39
A35: MARGEN sin registrar | B35: =(SUM(F22:F30)-803.9614)/SUM(F22:F30) -> 0.20960183 | L35: =IF(B35>=0.3,"APROBAR",IF(B35>=0.2,"REVISAR","RECHAZAR")) -> REVISAR
A37: Factura 8546 · C03270 · LULU BEACH CLUB JAVEA SL | I37: ES0021000001205457LR · Naturgy · 01/04/26 a 30/04/26 · PC maestro (=factura real, verificado) | R37: HISTÓRICO DEL CUPS · HOJA TTVA LUZ
A38: Concepto | B38: PENDIENTE (sin registrar) | H38: MES ANTERIOR (s/d) | L38: AÑO ANTERIOR (s/d) | R38: Cobrado total: 12.272 €
B39: Cant | C39: Días | D39: PC real | E39: PV | F39: Importe | H39: Cant | I39: PV | J39: Importe | L39: Cant | M39: PV | N39: Importe | R39: Pagado total: 9.764 €
A40: P1 Potencia | B40: 37 | C40: 30 | D40: 1.73784 | E40: 1.74 | F40: =ROUND(B40*E40,2) -> 64.38 | R40: DIF: 2.509 € · Margen hist.: 20.4%
A41: P2 Potencia | B41: 37 | C41: 30 | D41: 0.9357 | E41: 0.94 | F41: =ROUND(B41*E41,2) -> 34.78 | R41: Mejor mes: 2026-05 · 3.747 € · margen 22%
A42: P3 Potencia | B42: 37 | C42: 30 | D42: 0.43137 | E42: 0.43 | F42: =ROUND(B42*E42,2) -> 15.91 | R42: Peor mes: 2026-02 · 1.625 € · margen 27%
A43: P4 Potencia | B43: 37 | C43: 30 | D43: 0.38244 | E43: 0.38 | F43: =ROUND(B43*E43,2) -> 14.06 | R43: ✓ Lecturas 3/3 · productos · periodos OK
A44: P5 Potencia | B44: 37 | C44: 30 | D44: 0.26964 | E44: 0.27 | F44: =ROUND(B44*E44,2) -> 9.99 | R44: Importe mensual cobrado (€) · últimos 24 meses
A45: P6 Potencia | B45: 37 | C45: 30 | D45: 0.18156 | E45: 0.18 | F45: =ROUND(B45*E45,2) -> 6.66
A46: P4 Energía | B46: =IF($P$46="",5952.91,ROUND(5952.91*((2775.0294/(1-$P$46))-145.78)/2726,2)) -> 5952.91 | D46: 0.121236 | E46: 0.142 | F46: =ROUND(B46*E46,2) -> 845.31 | O46: Margen objetivo (edita el % aquí) ▶
A47: P5 Energía | B47: =IF($P$46="",4481.69,ROUND(4481.69*((2775.0294/(1-$P$46))-145.78)/2726,2)) -> 4481.69 | D47: 0.114444 | E47: 0.114 | F47: =ROUND(B47*E47,2) -> 510.91 | O47: Cant. P4/P5/P6 suben en proporción
A48: P6 Energía | B48: =IF($P$46="",13057.95,ROUND(13057.95*((2775.0294/(1-$P$46))-145.78)/2726,2)) -> 13057.95 | D48: 0.106808 | E48: 0.1049 | F48: =ROUND(B48*E48,2) -> 1369.78 | O48: para cumplir ese margen
A49: Alquiler contador | B49: 1 | D49: 6 | E49: 6 | F49: =ROUND(B49*E49,2) -> 6
A50: Bono social | B50: 30 | D50: 0.01912 | E50: 0.01912 | F50: =ROUND(B50*E50,2) -> 0.57
A51: Tasa eléctrica | B51: 155.12 | D51: 1 | E51: 1 | F51: =ROUND(B51*E51,2) -> 155.12
A52: TOTAL c/IVA | F52: =ROUND((SUM(F40:F51)-F51)*1.21+F51,2) -> 3637.92
A53: MARGEN sin registrar | B53: =(SUM(F40:F48)-2775.0294)/SUM(F40:F48) -> 0.033690116 | L53: =IF(B53>=0.3,"APROBAR",IF(B53>=0.2,"REVISAR","RECHAZAR")) -> RECHAZAR
A55: Factura 8547 · C01770 · CASA LILI JAVEA, S.L. | I55: ES0021000012742166PW · ? · 01/04/26 a 30/04/26 · PC real leído: 01ABR_30ABR26 (real) | R55: HISTÓRICO DEL CUPS · HOJA TTVA LUZ
A56: Concepto | B56: PENDIENTE (sin registrar) | H56: MES ANTERIOR · Fact.6081 (01/03/26 a 31/03/26) | L56: AÑO ANTERIOR · Fact.4142 (01/04/25 a 30/04/25) | R56: Cobrado total: 130.569 €
B57: Cant | C57: Días | D57: PC real | E57: PV | F57: Importe | H57: Cant | I57: PV | J57: Importe | L57: Cant | M57: PV | N57: Importe | R57: Pagado total: 74.176 €
A58: P1 Potencia | B58: 40 | C58: 30 | D58: 2.43249 | E58: 3.0517 | F58: =ROUND(B58*E58,2) -> 122.07 | H58: 40 | I58: 2.3922 | J58: =ROUND(H58*I58,2) -> 95.69 | L58: 40 | M58: 3.0517 | N58: =ROUND(L58*M58,2) -> 122.07 | R58: DIF: 56.393 € · Margen hist.: 43.2%
A59: P2 Potencia | B59: 40 | C59: 30 | D59: 1.27518 | E59: 1.8367 | F59: =ROUND(B59*E59,2) -> 73.47 | H59: 40 | I59: 2.0667 | J59: =ROUND(H59*I59,2) -> 82.67 | L59: 40 | M59: 1.8367 | N59: =ROUND(L59*M59,2) -> 73.47 | R59: Mejor mes: 2024-01 · 5.457 € · margen 28%
A60: P3 Potencia | B60: 40 | C60: 30 | D60: 0.55905 | E60: 1.4159 | F60: =ROUND(B60*E60,2) -> 56.64 | H60: 40 | I60: 1.0757 | J60: =ROUND(H60*I60,2) -> 43.03 | L60: 40 | M60: 1.4159 | N60: =ROUND(L60*M60,2) -> 56.64 | R60: Peor mes: 2026-01 · 2.917 € · margen 20%
A61: P4 Potencia | B61: 40 | C61: 30 | D61: 0.44334 | E61: 1.1559 | F61: =ROUND(B61*E61,2) -> 46.24 | H61: 40 | I61: 0.8917 | J61: =ROUND(H61*I61,2) -> 35.67 | L61: 40 | M61: 1.1559 | N61: =ROUND(L61*M61,2) -> 46.24 | R61: ✓ Lecturas 3/3 · productos · periodos OK
A62: P5 Potencia | B62: 40 | C62: 30 | D62: 0.17466 | E62: 0.2139 | F62: =ROUND(B62*E62,2) -> 8.56 | H62: 40 | I62: 0.2067 | J62: =ROUND(H62*I62,2) -> 8.27 | L62: 40 | M62: 0.2139 | N62: =ROUND(L62*M62,2) -> 8.56 | R62: Importe mensual cobrado (€) · últimos 24 meses
A63: P6 Potencia | B63: 40 | C63: 30 | D63: 0.08253 | E63: 0.1209 | F63: =ROUND(B63*E63,2) -> 4.84 | H63: 40 | I63: 0.1244 | J63: =ROUND(H63*I63,2) -> 4.98 | L63: 40 | M63: 0.1209 | N63: =ROUND(L63*M63,2) -> 4.84
A64: P4 Energía | B64: =IF($P$64="",5772.67,ROUND(5772.67*((1679.5979/(1-$P$64))-311.82)/2112.37,2)) -> 5772.67 | D64: 0.097753 | E64: 0.13 | F64: =ROUND(B64*E64,2) -> 750.45 | H64: 3991 | I64: 0.13 | J64: =ROUND(H64*I64,2) -> 518.83 | L64: 5772.67 | M64: 0.16 | N64: =ROUND(L64*M64,2) -> 923.63 | O64: Margen objetivo (edita el % aquí) ▶
A65: P5 Energía | B65: =IF($P$64="",4223.96,ROUND(4223.96*((1679.5979/(1-$P$64))-311.82)/2112.37,2)) -> 4223.96 | D65: 0.091419 | E65: 0.13 | F65: =ROUND(B65*E65,2) -> 549.11 | H65: 6530 | I65: 0.13 | J65: =ROUND(H65*I65,2) -> 848.9 | L65: 4223.96 | M65: 0.16 | N65: =ROUND(L65*M65,2) -> 675.83 | O65: Cant. P4/P5/P6 suben en proporción
A66: P6 Energía | B66: =IF($P$64="",6252.35,ROUND(6252.35*((1679.5979/(1-$P$64))-311.82)/2112.37,2)) -> 6252.35 | D66: 0.084842 | E66: 0.13 | F66: =ROUND(B66*E66,2) -> 812.81 | H66: 8909 | I66: 0.13 | J66: =ROUND(H66*I66,2) -> 1158.17 | L66: 6252.35 | M66: 0.16 | N66: =ROUND(L66*M66,2) -> 1000.38 | O66: para cumplir ese margen
A67: Alquiler contador | B67: 1 | D67: 17.615 | E67: 17.615 | F67: =ROUND(B67*E67,2) -> 17.62 | H67: 1 | I67: 17.615 | J67: =ROUND(H67*I67,2) -> 17.62 | L67: 1 | M67: 17.615 | N67: =ROUND(L67*M67,2) -> 17.62
A68: Bono social | B68: 30 | D68: 0.01274 | E68: 0.01274 | F68: =ROUND(B68*E68,2) -> 0.38 | H68: 30 | I68: 0.01274 | J68: =ROUND(H68*I68,2) -> 0.38 | L68: 30 | M68: 0.00629 | N68: =ROUND(L68*M68,2) -> 0.19
A69: Tasa eléctrica | B69: 132.29 | D69: 1 | E69: 1 | F69: =ROUND(B69*E69,2) -> 132.29 | H69: 152.79 | I69: 1 | J69: =ROUND(H69*I69,2) -> 152.79 | L69: 146.7 | M69: 1 | N69: =ROUND(L69*M69,2) -> 146.7
A70: Compensación excedentes | E70: sin venta
A71: TOTAL c/IVA | F71: =ROUND((SUM(F58:F70)-F69)*1.21+F69,2) -> 3087.34 | J71: =ROUND((SUM(J58:J70)-J69)*1.21+J69,2) -> 3557.98 | N71: =ROUND((SUM(N58:N70)-N69)*1.21+N69,2) -> 3691.36
A72: MARGEN sin registrar | B72: =(SUM(F58:F66)-1679.5979)/SUM(F58:F66) -> 0.30715088 | L72: =IF(B72>=0.3,"APROBAR",IF(B72>=0.2,"REVISAR","RECHAZAR")) -> APROBAR
A74: Factura 8564 · C01930 · FUNDACIÓN FSU PROGRAMAS INTERNACIONALES | I74: ES0021000008997144KR · Naturgy · 01/04/26 a 30/04/26 · PC maestro (=factura real, verificado) | R74: HISTÓRICO DEL CUPS · HOJA TTVA LUZ
A75: Concepto | B75: PENDIENTE (sin registrar) | H75: MES ANTERIOR · Fact.6300 (01/03/26 a 31/03/26) | L75: AÑO ANTERIOR · Fact.4598 (01/04/25 a 30/04/25) | R75: Cobrado total: 18.857 €
B76: Cant | C76: Días | D76: PC real | E76: PV | F76: Importe | H76: Cant | I76: PV | J76: Importe | L76: Cant | M76: PV | N76: Importe | R76: Pagado total: 13.790 €
A77: P1 Potencia | B77: 24.249 | C77: 30 | D77: 1.73784 | E77: 2.5542 | F77: =ROUND(B77*E77,2) -> 61.94 | H77: 24.249 | I77: 2.5542 | J77: =ROUND(H77*I77,2) -> 61.94 | L77: 24.249 | M77: 2.5542 | N77: =ROUND(L77*M77,2) -> 61.94 | R77: DIF: 5.067 € · Margen hist.: 26.9%
A78: P2 Potencia | B78: 24.249 | C78: 30 | D78: 0.9357 | E78: 1.3773 | F78: =ROUND(B78*E78,2) -> 33.4 | H78: 24.249 | I78: 1.3773 | J78: =ROUND(H78*I78,2) -> 33.4 | L78: 24.249 | M78: 1.3773 | N78: =ROUND(L78*M78,2) -> 33.4 | R78: Mejor mes: 2025-10 · 816 € · margen 30%
A79: P3 Potencia | B79: 24.249 | C79: 30 | D79: 0.43137 | E79: 0.6286 | F79: =ROUND(B79*E79,2) -> 15.24 | H79: 24.249 | I79: 0.6286 | J79: =ROUND(H79*I79,2) -> 15.24 | L79: 24.249 | M79: 0.6286 | N79: =ROUND(L79*M79,2) -> 15.24 | R79: Peor mes: 2024-02 · 408 € · margen 37%
A80: P4 Potencia | B80: 24.249 | C80: 30 | D80: 0.38244 | E80: 0.5561 | F80: =ROUND(B80*E80,2) -> 13.48 | H80: 24.249 | I80: 0.5561 | J80: =ROUND(H80*I80,2) -> 13.48 | L80: 24.249 | M80: 0.5561 | N80: =ROUND(L80*M80,2) -> 13.48 | R80: ✓ Lecturas 3/3 · productos · periodos OK
A81: P5 Potencia | B81: 24.249 | C81: 30 | D81: 0.26964 | E81: 0.3868 | F81: =ROUND(B81*E81,2) -> 9.38 | H81: 24.249 | I81: 0.3868 | J81: =ROUND(H81*I81,2) -> 9.38 | L81: 24.249 | M81: 0.3868 | N81: =ROUND(L81*M81,2) -> 9.38 | R81: Importe mensual cobrado (€) · últimos 24 meses
A82: P6 Potencia | B82: 24.249 | C82: 30 | D82: 0.18156 | E82: 0.2653 | F82: =ROUND(B82*E82,2) -> 6.43 | H82: 24.249 | I82: 0.2653 | J82: =ROUND(H82*I82,2) -> 6.43 | L82: 24.249 | M82: 0.2653 | N82: =ROUND(L82*M82,2) -> 6.43
A83: P4 Energía | B83: =IF($P$83="",764.02,ROUND(764.02*((372.2018/(1-$P$83))-139.87)/440.41,2)) -> 764.02 | D83: 0.106808 | E83: 0.17 | F83: =ROUND(B83*E83,2) -> 129.88 | H83: 692.323 | I83: 0.175 | J83: =ROUND(H83*I83,2) -> 121.16 | L83: 564.02 | M83: 0.175 | N83: =ROUND(L83*M83,2) -> 98.7 | O83: Margen objetivo (edita el % aquí) ▶
A84: P5 Energía | B84: =IF($P$83="",566.81,ROUND(566.81*((372.2018/(1-$P$83))-139.87)/440.41,2)) -> 566.81 | D84: 0.106808 | E84: 0.17 | F84: =ROUND(B84*E84,2) -> 96.36 | H84: 678.691 | I84: 0.175 | J84: =ROUND(H84*I84,2) -> 118.77 | L84: 466.81 | M84: 0.175 | N84: =ROUND(L84*M84,2) -> 81.69 | O84: Cant. P4/P5/P6 suben en proporción
A85: P6 Energía | B85: =IF($P$83="",1259.797,ROUND(1259.797*((372.2018/(1-$P$83))-139.87)/440.41,2)) -> 1259.797 | D85: 0.106808 | E85: 0.17 | F85: =ROUND(B85*E85,2) -> 214.17 | H85: 1399.94 | I85: 0.175 | J85: =ROUND(H85*I85,2) -> 244.99 | L85: 959.797 | M85: 0.175 | N85: =ROUND(L85*M85,2) -> 167.96 | O85: para cumplir ese margen
A86: Alquiler contador | B86: 1 | D86: 6 | E86: 6 | F86: =ROUND(B86*E86,2) -> 6 | H86: 1 | I86: 6 | J86: =ROUND(H86*I86,2) -> 6 | L86: 1 | M86: 6 | N86: =ROUND(L86*M86,2) -> 6
A87: Bono social | B87: 30 | D87: 0.01274 | E87: 0.01274 | F87: =ROUND(B87*E87,2) -> 0.38 | H87: 30 | I87: 0.00629 | J87: =ROUND(H87*I87,2) -> 0.19 | L87: 30 | M87: 0.00629 | N87: =ROUND(L87*M87,2) -> 0.19
A88: Tasa eléctrica | B88: 31.32 | D88: 1 | E88: 1 | F88: =ROUND(B88*E88,2) -> 31.32 | H88: 27.75 | I88: 1 | J88: =ROUND(H88*I88,2) -> 27.75 | L88: 26.26 | M88: 1 | N88: =ROUND(L88*M88,2) -> 26.26
A89: TOTAL c/IVA | F89: =ROUND((SUM(F77:F88)-F88)*1.21+F88,2) -> 741.18 | J89: =ROUND((SUM(J77:J88)-J88)*1.21+J88,2) -> 791.24 | N89: =ROUND((SUM(N77:N88)-N88)*1.21+N88,2) -> 624.5
A90: MARGEN sin registrar | B90: =(SUM(F77:F85)-372.2018)/SUM(F77:F85) -> 0.35858241 | L90: =IF(B90>=0.3,"APROBAR",IF(B90>=0.2,"REVISAR","RECHAZAR")) -> APROBAR
A92: Factura 8565 · C01920 · FUNDACIÓN FSU PROGRAMAS INTERNACIONALES | I92: ES0021000020111643FA · Naturgy · 01/04/26 a 30/04/26 · PC real leído: mismo contrato FSU (precio fijo) | R92: HISTÓRICO DEL CUPS · HOJA TTVA LUZ
A93: Concepto | B93: PENDIENTE (sin registrar) | H93: MES ANTERIOR · Fact.6299 (01/03/26 a 31/03/26) | L93: AÑO ANTERIOR · Fact.4599 (01/04/25 a 30/04/25) | R93: Cobrado total: 19.336 €
B94: Cant | C94: Días | D94: PC real | E94: PV | F94: Importe | H94: Cant | I94: PV | J94: Importe | L94: Cant | M94: PV | N94: Importe | R94: Pagado total: 13.069 €
A95: P1 Potencia | B95: 17.32 | C95: 30 | D95: 1.73784 | E95: 2.5542 | F95: =ROUND(B95*E95,2) -> 44.24 | H95: 17.32 | I95: 2.5542 | J95: =ROUND(H95*I95,2) -> 44.24 | L95: 17.32 | M95: 2.5542 | N95: =ROUND(L95*M95,2) -> 44.24 | R95: DIF: 6.267 € · Margen hist.: 32.4%
A96: P2 Potencia | B96: 17.32 | C96: 30 | D96: 0.9357 | E96: 1.3773 | F96: =ROUND(B96*E96,2) -> 23.85 | H96: 17.32 | I96: 1.3773 | J96: =ROUND(H96*I96,2) -> 23.85 | L96: 17.32 | M96: 1.3773 | N96: =ROUND(L96*M96,2) -> 23.85 | R96: Mejor mes: 2026-03 · 1.019 € · margen 57%
A97: P3 Potencia | B97: 17.32 | C97: 30 | D97: 0.43137 | E97: 0.6286 | F97: =ROUND(B97*E97,2) -> 10.89 | H97: 17.32 | I97: 0.6286 | J97: =ROUND(H97*I97,2) -> 10.89 | L97: 17.32 | M97: 0.6286 | N97: =ROUND(L97*M97,2) -> 10.89 | R97: Peor mes: 2024-12 · 207 € · margen -183%
A98: P4 Potencia | B98: 17.32 | C98: 30 | D98: 0.38244 | E98: 0.5561 | F98: =ROUND(B98*E98,2) -> 9.63 | H98: 17.32 | I98: 0.5561 | J98: =ROUND(H98*I98,2) -> 9.63 | L98: 17.32 | M98: 0.5561 | N98: =ROUND(L98*M98,2) -> 9.63 | R98: ✓ Lecturas 3/3 · productos · periodos OK
A99: P5 Potencia | B99: 17.32 | C99: 30 | D99: 0.26964 | E99: 0.3868 | F99: =ROUND(B99*E99,2) -> 6.7 | H99: 17.32 | I99: 0.3868 | J99: =ROUND(H99*I99,2) -> 6.7 | L99: 17.32 | M99: 0.3868 | N99: =ROUND(L99*M99,2) -> 6.7 | R99: Importe mensual cobrado (€) · últimos 24 meses
A100: P6 Potencia | B100: 17.32 | C100: 30 | D100: 0.18156 | E100: 0.2653 | F100: =ROUND(B100*E100,2) -> 4.59 | H100: 17.32 | I100: 0.2653 | J100: =ROUND(H100*I100,2) -> 4.59 | L100: 17.32 | M100: 0.2653 | N100: =ROUND(L100*M100,2) -> 4.59
A101: P4 Energía | B101: =IF($P$101="",678.02,ROUND(678.02*((357.0888/(1-$P$101))-99.9)/436.56,2)) -> 678.02 | D101: 0.121236 | E101: 0.17 | F101: =ROUND(B101*E101,2) -> 115.26 | H101: 1040.151 | I101: 0.175 | J101: =ROUND(H101*I101,2) -> 182.03 | L101: 578.02 | M101: 0.175 | N101: =ROUND(L101*M101,2) -> 101.15 | O101: Margen objetivo (edita el % aquí) ▶
A102: P5 Energía | B102: =IF($P$101="",629.871,ROUND(629.871*((357.0888/(1-$P$101))-99.9)/436.56,2)) -> 629.871 | D102: 0.114444 | E102: 0.17 | F102: =ROUND(B102*E102,2) -> 107.08 | H102: 770.551 | I102: 0.175 | J102: =ROUND(H102*I102,2) -> 134.85 | L102: 429.871 | M102: 0.175 | N102: =ROUND(L102*M102,2) -> 75.23 | O102: Cant. P4/P5/P6 suben en proporción
A103: P6 Energía | B103: =IF($P$101="",1260.09,ROUND(1260.09*((357.0888/(1-$P$101))-99.9)/436.56,2)) -> 1260.09 | D103: 0.106808 | E103: 0.17 | F103: =ROUND(B103*E103,2) -> 214.22 | H103: 2191.12 | I103: 0.175 | J103: =ROUND(H103*I103,2) -> 383.45 | L103: 1060.09 | M103: 0.175 | N103: =ROUND(L103*M103,2) -> 185.52 | O103: para cumplir ese margen
A104: Alquiler contador | B104: 1 | D104: 6 | E104: 6 | F104: =ROUND(B104*E104,2) -> 6 | H104: 1 | I104: 6 | J104: =ROUND(H104*I104,2) -> 6 | L104: 1 | M104: 6 | N104: =ROUND(L104*M104,2) -> 6
A105: Bono social | B105: 30 | D105: 0.00629 | E105: 0.00629 | F105: =ROUND(B105*E105,2) -> 0.19 | H105: 30 | I105: 0.01274 | J105: =ROUND(H105*I105,2) -> 0.38 | L105: 30 | M105: 0.00629 | N105: =ROUND(L105*M105,2) -> 0.19
...

Sheet _series
A1: nf | B1: 2024-07 | C1: 2024-08 | D1: 2024-09 | E1: 2024-10 | F1: 2024-11 | G1: 2024-12 | H1: 2025-01 | I1: 2025-02 | J1: 2025-03 | K1: 2025-04 | L1: 2025-05 | M1: 2025-06 | N1: 2025-07 | O1: 2025-08 | P1: 2025-09 | Q1: 2025-10 | R1: 2025-11 | S1: 2025-12 | T1: 2026-01 | U1: 2026-02 | V1: 2026-03 | W1: 2026-04 | X1: 2026-05 | Y1: 2026-06
A2: 8544 | B2: 1823.2 | C2: 2200.79 | D2: 1506.86 | E2: 1294.73 | F2: 701.24 | G2: 2057.58 | H2: 704.65 | I2: 1131.33 | J2: 1195.22 | K2: 1397.39 | L2: 1489.78 | M2: 1604.92 | N2: 2264.68 | O2: 2392.22 | P2: 1906.5 | Q2: 1541.7 | R2: 1553.06 | S2: 1623.98 | T2: 1669.87 | U2: 1287.26 | V2: 1560.23 | W2: 1696.52 | X2: 1398.99 | Y2: 1699.39
A3: 8545 | B3: 2278.23 | C3: 2606.49 | D3: 1372.78 | E3: 1218.04 | F3: 852.42 | G3: 892.96 | H3: 526.46 | I3: 703.02 | J3: 973.88 | K3: 1071.5 | L3: 1198.45 | M3: 1352.91 | N3: 2137.78 | O3: 2576.37 | P3: 1966.13 | Q3: 1508.21 | R3: 982.22 | S3: 980.76 | T3: 639.12 | U3: 1081.39 | V3: 1166.31 | W3: 1408.31 | X3: 1317.52 | Y3: 0
A4: 8546 | B4: 0 | C4: 0 | D4: 0 | E4: 0 | F4: 0 | G4: 0 | H4: 0 | I4: 0 | J4: 0 | K4: 0 | L4: 0 | M4: 0 | N4: 0 | O4: 0 | P4: 0 | Q4: 0 | R4: 0 | S4: 0 | T4: 0 | U4: 1625.21 | V4: 3262.26 | W4: 3637.92 | X4: 3747.07 | Y4: 0
A5: 8547 | B5: 4696.57 | C5: 5119.32 | D5: 3940.09 | E5: 4434.05 | F5: 4230.84 | G5: 4056.83 | H5: 3691.35 | I5: 4434.05 | J5: 4606.23 | K5: 3691.35 | L5: 3472.32 | M5: 3278.22 | N5: 4267.48 | O5: 4424.02 | P5: 3939.03 | Q5: 3404.76 | R5: 3733.87 | S5: 3769.58 | T5: 2917.21 | U5: 3522.69 | V5: 3557.98 | W5: 3087.33 | X5: 3133.52 | Y5: 3743.04
A6: 8564 | B6: 643.79 | C6: 476.53 | D6: 592.3 | E6: 631.06 | F6: 457.49 | G6: 578.16 | H6: 596.33 | I6: 602.79 | J6: 791.23 | K6: 624.49 | L6: 601.33 | M6: 711.31 | N6: 738.16 | O6: 605.43 | P6: 803.47 | Q6: 816.36 | R6: 572.69 | S6: 690.5 | T6: 712.22 | U6: 695.09 | V6: 791.23 | W6: 741.17 | X6: 782.58 | Y6: 755.25
A7: 8565 | B7: 632.44 | C7: 592.69 | D7: 610.04 | E7: 632.66 | F7: 637.18 | G7: 207.37 | H7: 706.19 | I7: 645.52 | J7: 899.33 | K7: 591.1 | L7: 643.89 | M7: 696.92 | N7: 731.73 | O7: 688.65 | P7: 794.97 | Q7: 824.16 | R7: 684.8 | S7: 331.28 | T7: 819.21 | U7: 753.83 | V7: 1018.62 | W7: 685.61 | X7: 741.79 | Y7: 789.76
A8: 8566 | B8: 524.5 | C8: 166.78 | D8: 444.46 | E8: 345.59 | F8: 0 | G8: 233.91 | H8: 294.11 | I8: 270.48 | J8: 383.23 | K8: 290.33 | L8: 336.88 | M8: 502.61 | N8: 634.9 | O8: 239.55 | P8: 628.5 | Q8: 440.92 | R8: 411.49 | S8: 407.39 | T8: 420.96 | U8: 391.83 | V8: 427.24 | W8: 354.48 | X8: 412.63 | Y8: 593.22
A9: 8567 | B9: 4475.16 | C9: 4612.54 | D9: 3701.38 | E9: 4561.47 | F9: 3334.09 | G9: 3216.6 | H9: 2924.41 | I9: 2743.54 | J9: 3702.5 | K9: 3817.43 | L9: 3300.04 | M9: 2798.1 | N9: 3784.48 | O9: 3716.14 | P9: 3334.45 | Q9: 3275.16 | R9: 3190.07 | S9: 2956.24 | T9: 2736.06 | U9: 2890.35 | V9: 3365.79 | W9: 2721.04 | X9: 2640.22 | Y9: 3260.09
A10: 8578 | B10: 151.82 | C10: 199.06 | D10: 183.84 | E10: 178.12 | F10: 184.03 | G10: 163.02 | H10: 136.55 | I10: 104.41 | J10: 98.7 | K10: 40.05 | L10: 67.35 | M10: 65.71 | N10: 361.06 | O10: 201.13 | P10: 85.6 | Q10: 63.93 | R10: 60.72 | S10: 51.57 | T10: 43.55 | U10: 40.37 | V10: 82.31 | W10: 38.53 | X10: 39.81 | Y10: 0
A11: 8615 | B11: 1167.19 | C11: 1131.86 | D11: 610.86 | E11: 553.94 | F11: 544.65 | G11: 727.09 | H11: 952.35 | I11: 581.27 | J11: 746.2 | K11: 543.77 | L11: 442.06 | M11: 643.81 | N11: 881.89 | O11: 963.15 | P11: 800.92 | Q11: 588.39 | R11: 478.95 | S11: 812.61 | T11: 783.67 | U11: 595.95 | V11: 634.87 | W11: 433.2 | X11: 544.11 | Y11: 0
A12: 8629 | B12: 128.85 | C12: 119.74 | D12: 120.37 | E12: 126 | F12: 121.75 | G12: 129.12 | H12: 118.2 | I12: 116.61 | J12: 118.21 | K12: 118.11 | L12: 120.31 | M12: 110.46 | N12: 126.3 | O12: 120.84 | P12: 118.41 | Q12: 110.34 | R12: 143.28 | S12: 123.63 | T12: 117.54 | U12: 119.84 | V12: 122.01 | W12: 115.84 | X12: 0 | Y12: 0
A13: 8635 | B13: 1506.8 | C13: 1792.99 | D13: 833.07 | E13: 766.01 | F13: 194.02 | G13: 665.19 | H13: 676.36 | I13: 603.95 | J13: 730.96 | K13: 678.97 | L13: 774.09 | M13: 774.72 | N13: 1594.97 | O13: 1863.52 | P13: 1379.87 | Q13: 902.28 | R13: 243.48 | S13: 790.46 | T13: 762.17 | U13: 615.97 | V13: 542.6 | W13: 641.56 | X13: 747.69 | Y13: 0
... A28: 8738 | B28: 0 | C28: 0 | D28: 0 | E28: 0 | F28: 1197.18 | G28: 1865.97 | H28: 1723.16 | I28: 1570.31 | J28: 1432.73 | K28: 1817.32 | L28: 1955.83 | M28: 2235.47 | N28: 2825.24 | O28: 3443.22 | P28: 3178.08 | Q28: 2134.16 | R28: 1883.16 | S28: 1916.12 | T28: 1372.39 | U28: 2844.42 | V28: 2594.23 | W28: 2436.29 | X28: 2434.85 | Y28: 0
